{"userId":"user8","date":"09-08-2023-05-44-21","gameName":"OhShape","mode":"PRACTICE","numberOfRounds":1,"numberOfShapes":16,"shapeIndexs":[5,5,0,0,1,1,6,6,2,2,3,3,7,7,4,4],"roundNumber":0,"numberOfCollusions":451,"collusionData":[{"actutorId":96,"timestamp":456.0999755859375,"duration":0.030029296875,"other":"shape0","detail":"Cube.007"},{"actutorId":71,"timestamp":456.0799865722656,"duration":0.089996337890625,"other":"shape0","detail":"Cube.007"},{"actutorId":164,"timestamp":456.16998291015627,"duration":0.010009765625,"other":"shape0","detail":"Cube.020"},{"actutorId":102,"timestamp":456.0299987792969,"duration":0.19000244140625,"other":"shape0","detail":"Cube.007"},{"actutorId":97,"timestamp":456.0299987792969,"duration":0.28997802734375,"other":"shape0","detail":"Cube.007"},{"actutorId":133,"timestamp":456.0999755859375,"duration":0.1400146484375,"other":"shape0","detail":"Cube.020"},{"actutorId":98,"timestamp":455.989990234375,"duration":0.3699951171875,"other":"shape0","detail":"Cube.007"},{"actutorId":159,"timestamp":456.0799865722656,"duration":0.399993896484375,"other":"shape0","detail":"Cube.020"},{"actutorId":97,"timestamp":456.0299987792969,"duration":0.28997802734375,"other":"shape0","detail":"Cube.007"},{"actutorId":163,"timestamp":456.05999755859377,"duration":0.259979248046875,"other":"shape0","detail":"Cube.020"},{"actutorId":132,"timestamp":456.03997802734377,"duration":0.290008544921875,"other":"shape0","detail":"Cube.020"},{"actutorId":101,"timestamp":455.92999267578127,"duration":0.42999267578125,"other":"shape0","detail":"Cube.007"},{"actutorId":98,"timestamp":455.989990234375,"duration":0.3699951171875,"other":"shape0","detail":"Cube.007"},{"actutorId":162,"timestamp":456.0199890136719,"duration":0.350006103515625,"other":"shape0","detail":"Cube.020"},{"actutorId":153,"timestamp":456.03997802734377,"duration":0.350006103515625,"other":"shape0","detail":"Cube.036"},{"actutorId":154,"timestamp":456.05999755859377,"duration":0.47998046875,"other":"shape0","detail":"Cube.034"},{"actutorId":99,"timestamp":455.91998291015627,"duration":0.470001220703125,"other":"shape0","detail":"Cube.007"},{"actutorId":131,"timestamp":455.989990234375,"duration":0.399993896484375,"other":"shape0","detail":"Cube.020"},{"actutorId":100,"timestamp":455.8899841308594,"duration":0.510009765625,"other":"shape0","detail":"Cube.007"},{"actutorId":161,"timestamp":455.989990234375,"duration":0.410003662109375,"other":"shape0","detail":"Cube.020"},{"actutorId":160,"timestamp":455.9599914550781,"duration":0.510009765625,"other":"shape0","detail":"Cube.020"},{"actutorId":155,"timestamp":456.0299987792969,"duration":0.449981689453125,"other":"shape0","detail":"Cube.020"},{"actutorId":159,"timestamp":456.0799865722656,"duration":0.399993896484375,"other":"shape0","detail":"Cube.020"},{"actutorId":155,"timestamp":456.0299987792969,"duration":0.449981689453125,"other":"shape0","detail":"Cube.020"},{"actutorId":156,"timestamp":456.0199890136719,"duration":0.480010986328125,"other":"shape0","detail":"Cube.020"},{"actutorId":158,"timestamp":455.989990234375,"duration":0.510009765625,"other":"shape0","detail":"Cube.020"},{"actutorId":157,"timestamp":456.0,"duration":0.529998779296875,"other":"shape0","detail":"Cube.020"},{"actutorId":154,"timestamp":456.05999755859377,"duration":0.47998046875,"other":"shape0","detail":"Cube.034"},{"actutorId":154,"timestamp":456.05999755859377,"duration":0.47998046875,"other":"shape0","detail":"Cube.034"},{"actutorId":64,"timestamp":456.6399841308594,"duration":0.170013427734375,"other":"shape0","detail":"Cube.025"},{"actutorId":78,"timestamp":456.6300048828125,"duration":0.219970703125,"other":"shape0","detail":"Cube.025"},{"actutorId":163,"timestamp":456.7699890136719,"duration":0.100006103515625,"other":"shape0","detail":"Cube.019"},{"actutorId":63,"timestamp":456.6099853515625,"duration":0.279998779296875,"other":"shape0","detail":"Cube.025"},{"actutorId":134,"timestamp":457.0,"duration":0.03997802734375,"other":"shape0","detail":"Cube.019"},{"actutorId":163,"timestamp":456.9599914550781,"duration":0.1099853515625,"other":"shape0","detail":"Cube.019"},{"actutorId":133,"timestamp":456.7699890136719,"duration":0.30999755859375,"other":"shape0","detail":"Cube.019"},{"actutorId":132,"timestamp":456.75,"duration":0.3499755859375,"other":"shape0","detail":"Cube.019"},{"actutorId":162,"timestamp":456.75,"duration":0.3499755859375,"other":"shape0","detail":"Cube.019"},{"actutorId":63,"timestamp":456.97998046875,"duration":0.1300048828125,"other":"shape0","detail":"Cube.025"},{"actutorId":131,"timestamp":456.72998046875,"duration":0.3800048828125,"other":"shape0","detail":"Cube.019"},{"actutorId":161,"timestamp":456.72998046875,"duration":0.3800048828125,"other":"shape0","detail":"Cube.019"},{"actutorId":122,"timestamp":456.7200012207031,"duration":0.42999267578125,"other":"shape0","detail":"Cube.019"},{"actutorId":129,"timestamp":456.66998291015627,"duration":0.510009765625,"other":"shape0","detail":"Cube.019"},{"actutorId":130,"timestamp":456.66998291015627,"duration":0.510009765625,"other":"shape0","detail":"Cube.019"},{"actutorId":123,"timestamp":456.67999267578127,"duration":0.5,"other":"shape0","detail":"Cube.019"},{"actutorId":124,"timestamp":456.66998291015627,"duration":0.52001953125,"other":"shape0","detail":"Cube.019"},{"actutorId":125,"timestamp":456.6499938964844,"duration":0.540008544921875,"other":"shape0","detail":"Cube.019"},{"actutorId":62,"timestamp":456.5699768066406,"duration":0.620025634765625,"other":"shape0","detail":"Cube.025"},{"actutorId":79,"timestamp":456.55999755859377,"duration":0.6300048828125,"other":"shape0","detail":"Cube.025"},{"actutorId":127,"timestamp":456.6399841308594,"duration":0.550018310546875,"other":"shape0","detail":"Cube.019"},{"actutorId":128,"timestamp":456.6499938964844,"duration":0.540008544921875,"other":"shape0","detail":"Cube.019"},{"actutorId":126,"timestamp":456.6300048828125,"duration":0.579986572265625,"other":"shape0","detail":"Cube.019"},{"actutorId":61,"timestamp":456.53997802734377,"duration":0.760009765625,"other":"shape0","detail":"Cube.025"},{"actutorId":80,"timestamp":456.5,"duration":0.8699951171875,"other":"shape0","detail":"Cube.025"},{"actutorId":101,"timestamp":461.78997802734377,"duration":0.05999755859375,"other":"shape1","detail":"Cube.011"},{"actutorId":69,"timestamp":461.8199768066406,"duration":0.1400146484375,"other":"shape1","detail":"Cube.007"},{"actutorId":105,"timestamp":461.8800048828125,"duration":0.05999755859375,"other":"shape1","detail":"Cube.011"},{"actutorId":69,"timestamp":461.8199768066406,"duration":0.1400146484375,"other":"shape1","detail":"Cube.007"},{"actutorId":73,"timestamp":461.9100036621094,"duration":0.04998779296875,"other":"shape1","detail":"Cube.007"},{"actutorId":72,"timestamp":461.8800048828125,"duration":0.199981689453125,"other":"shape1","detail":"Cube.011"},{"actutorId":104,"timestamp":461.8800048828125,"duration":0.199981689453125,"other":"shape1","detail":"Cube.011"},{"actutorId":155,"timestamp":462.3800048828125,"duration":0.459991455078125,"other":"shape1","detail":"Cube.020"},{"actutorId":104,"timestamp":462.1300048828125,"duration":1.069976806640625,"other":"shape1","detail":"Cube.011"},{"actutorId":158,"timestamp":462.4599914550781,"duration":0.3800048828125,"other":"shape1","detail":"Cube.020"},{"actutorId":75,"timestamp":462.489990234375,"duration":0.489990234375,"other":"shape1","detail":"Cube.011"},{"actutorId":132,"timestamp":462.3999938964844,"duration":0.199981689453125,"other":"shape1","detail":"Cube.020"},{"actutorId":164,"timestamp":462.3800048828125,"duration":0.219970703125,"other":"shape1","detail":"Cube.020"},{"actutorId":131,"timestamp":462.3299865722656,"duration":0.300018310546875,"other":"shape1","detail":"Cube.020"},{"actutorId":163,"timestamp":462.3299865722656,"duration":0.300018310546875,"other":"shape1","detail":"Cube.020"},{"actutorId":97,"timestamp":461.94000244140627,"duration":0.720001220703125,"other":"shape1","detail":"Cube.007"},{"actutorId":91,"timestamp":462.3800048828125,"duration":0.279998779296875,"other":"shape1","detail":"Cube.011"},{"actutorId":152,"timestamp":462.3999938964844,"duration":0.260009765625,"other":"shape1","detail":"Cube.036"},{"actutorId":161,"timestamp":462.29998779296877,"duration":0.360015869140625,"other":"shape1","detail":"Cube.020"},{"actutorId":162,"timestamp":462.29998779296877,"duration":0.360015869140625,"other":"shape1","detail":"Cube.020"},{"actutorId":154,"timestamp":462.0999755859375,"duration":0.83001708984375,"other":"shape1","detail":"Cube.031"},{"actutorId":154,"timestamp":462.0999755859375,"duration":0.83001708984375,"other":"shape1","detail":"Cube.031"},{"actutorId":160,"timestamp":462.1600036621094,"duration":0.5999755859375,"other":"shape1","detail":"Cube.020"},{"actutorId":159,"timestamp":462.0099792480469,"duration":0.779998779296875,"other":"shape1","detail":"Cube.020"},{"actutorId":158,"timestamp":462.4599914550781,"duration":0.3800048828125,"other":"shape1","detail":"Cube.020"},{"actutorId":155,"timestamp":462.3800048828125,"duration":0.459991455078125,"other":"shape1","detail":"Cube.020"},{"actutorId":156,"timestamp":462.03997802734377,"duration":0.80999755859375,"other":"shape1","detail":"Cube.020"},{"actutorId":153,"timestamp":462.0999755859375,"duration":0.8800048828125,"other":"shape1","detail":"Cube.034"},{"actutorId":157,"timestamp":462.03997802734377,"duration":0.850006103515625,"other":"shape1","detail":"Cube.020"},{"actutorId":66,"timestamp":462.5999755859375,"duration":0.290008544921875,"other":"shape1","detail":"Cube.011"},{"actutorId":70,"timestamp":462.6300048828125,"duration":0.529998779296875,"other":"shape1","detail":"Cube.007"},{"actutorId":76,"timestamp":462.5799865722656,"duration":0.30999755859375,"other":"shape1","detail":"Cube.011"},{"actutorId":154,"timestamp":462.0999755859375,"duration":0.83001708984375,"other":"shape1","detail":"Cube.031"},{"actutorId":154,"timestamp":462.0999755859375,"duration":0.83001708984375,"other":"shape1","detail":"Cube.031"},{"actutorId":100,"timestamp":462.5799865722656,"duration":0.589996337890625,"other":"shape1","detail":"Cube.007"},{"actutorId":108,"timestamp":462.5199890136719,"duration":0.410003662109375,"other":"shape1","detail":"Cube.011"},{"actutorId":67,"timestamp":462.5199890136719,"duration":0.459991455078125,"other":"shape1","detail":"Cube.007"},{"actutorId":67,"timestamp":462.5199890136719,"duration":0.459991455078125,"other":"shape1","detail":"Cube.007"},{"actutorId":75,"timestamp":462.489990234375,"duration":0.489990234375,"other":"shape1","detail":"Cube.011"},{"actutorId":153,"timestamp":462.0999755859375,"duration":0.8800048828125,"other":"shape1","detail":"Cube.034"},{"actutorId":153,"timestamp":462.0999755859375,"duration":0.8800048828125,"other":"shape1","detail":"Cube.034"},{"actutorId":107,"timestamp":462.42999267578127,"duration":0.589996337890625,"other":"shape1","detail":"Cube.011"},{"actutorId":91,"timestamp":462.8399963378906,"duration":0.47998046875,"other":"shape1","detail":"Cube.010"},{"actutorId":101,"timestamp":462.489990234375,"duration":0.649993896484375,"other":"shape1","detail":"Cube.011"},{"actutorId":101,"timestamp":462.489990234375,"duration":0.649993896484375,"other":"shape1","detail":"Cube.011"},{"actutorId":70,"timestamp":462.6300048828125,"duration":0.529998779296875,"other":"shape1","detail":"Cube.007"},{"actutorId":69,"timestamp":462.29998779296877,"duration":0.8699951171875,"other":"shape1","detail":"Cube.007"},{"actutorId":69,"timestamp":462.29998779296877,"duration":0.8699951171875,"other":"shape1","detail":"Cube.007"},{"actutorId":102,"timestamp":461.8199768066406,"duration":1.350006103515625,"other":"shape1","detail":"Cube.011"},{"actutorId":102,"timestamp":461.8199768066406,"duration":1.350006103515625,"other":"shape1","detail":"Cube.011"},{"actutorId":100,"timestamp":462.5799865722656,"duration":0.589996337890625,"other":"shape1","detail":"Cube.007"},{"actutorId":68,"timestamp":462.42999267578127,"duration":0.760009765625,"other":"shape1","detail":"Cube.007"},{"actutorId":68,"timestamp":462.42999267578127,"duration":0.760009765625,"other":"shape1","detail":"Cube.007"},{"actutorId":71,"timestamp":461.8199768066406,"duration":1.370025634765625,"other":"shape1","detail":"Cube.007"},{"actutorId":103,"timestamp":461.8499755859375,"duration":1.34002685546875,"other":"shape1","detail":"Cube.007"},{"actutorId":103,"timestamp":461.8499755859375,"duration":1.34002685546875,"other":"shape1","detail":"Cube.007"},{"actutorId":104,"timestamp":462.1300048828125,"duration":1.069976806640625,"other":"shape1","detail":"Cube.011"},{"actutorId":99,"timestamp":461.8499755859375,"duration":1.350006103515625,"other":"shape1","detail":"Cube.007"},{"actutorId":99,"timestamp":461.8499755859375,"duration":1.350006103515625,"other":"shape1","detail":"Cube.007"},{"actutorId":72,"timestamp":462.2099914550781,"duration":1.010009765625,"other":"shape1","detail":"Cube.011"},{"actutorId":72,"timestamp":462.2099914550781,"duration":1.010009765625,"other":"shape1","detail":"Cube.011"},{"actutorId":105,"timestamp":462.2699890136719,"duration":0.95001220703125,"other":"shape1","detail":"Cube.011"},{"actutorId":98,"timestamp":461.8800048828125,"duration":1.3499755859375,"other":"shape1","detail":"Cube.007"},{"actutorId":98,"timestamp":461.8800048828125,"duration":1.3499755859375,"other":"shape1","detail":"Cube.007"},{"actutorId":73,"timestamp":462.3299865722656,"duration":0.92999267578125,"other":"shape1","detail":"Cube.007"},{"actutorId":106,"timestamp":462.3800048828125,"duration":0.8599853515625,"other":"shape1","detail":"Cube.011"},{"actutorId":73,"timestamp":462.3299865722656,"duration":0.92999267578125,"other":"shape1","detail":"Cube.007"},{"actutorId":97,"timestamp":462.8499755859375,"duration":0.410003662109375,"other":"shape1","detail":"Cube.007"},{"actutorId":97,"timestamp":462.8499755859375,"duration":0.410003662109375,"other":"shape1","detail":"Cube.007"},{"actutorId":107,"timestamp":463.19000244140627,"duration":0.069976806640625,"other":"shape1","detail":"Cube.011"},{"actutorId":74,"timestamp":462.42999267578127,"duration":0.850006103515625,"other":"shape1","detail":"Cube.007"},{"actutorId":74,"timestamp":462.42999267578127,"duration":0.850006103515625,"other":"shape1","detail":"Cube.007"},{"actutorId":96,"timestamp":461.94000244140627,"duration":1.339996337890625,"other":"shape1","detail":"Cube.011"},{"actutorId":95,"timestamp":461.97998046875,"duration":1.33001708984375,"other":"shape1","detail":"Cube.011"},{"actutorId":157,"timestamp":463.29998779296877,"duration":0.019989013671875,"other":"shape1","detail":"Cube.020"},{"actutorId":91,"timestamp":462.8399963378906,"duration":0.47998046875,"other":"shape1","detail":"Cube.010"},{"actutorId":94,"timestamp":462.0099792480469,"duration":1.339996337890625,"other":"shape1","detail":"Cube.011"},{"actutorId":93,"timestamp":462.03997802734377,"duration":1.33001708984375,"other":"shape1","detail":"Cube.011"},{"actutorId":154,"timestamp":463.22998046875,"duration":0.1500244140625,"other":"shape1","detail":"Cube.031"},{"actutorId":154,"timestamp":463.22998046875,"duration":0.1500244140625,"other":"shape1","detail":"Cube.031"},{"actutorId":153,"timestamp":463.3499755859375,"duration":0.050018310546875,"other":"shape1","detail":"Cube.035"},{"actutorId":92,"timestamp":462.4599914550781,"duration":0.94000244140625,"other":"shape1","detail":"Cube.010"},{"actutorId":92,"timestamp":462.4599914550781,"duration":0.94000244140625,"other":"shape1","detail":"Cube.010"},{"actutorId":153,"timestamp":463.3499755859375,"duration":0.050018310546875,"other":"shape1","detail":"Cube.035"},{"actutorId":153,"timestamp":463.3499755859375,"duration":0.050018310546875,"other":"shape1","detail":"Cube.035"},{"actutorId":76,"timestamp":466.75,"duration":0.16998291015625,"other":"shape2","detail":"Cube.006"},{"actutorId":155,"timestamp":466.7699890136719,"duration":0.410003662109375,"other":"shape2","detail":"Cube.017"},{"actutorId":136,"timestamp":466.6999816894531,"duration":0.55999755859375,"other":"shape2","detail":"Cube.017"},{"actutorId":63,"timestamp":467.2200012207031,"duration":0.209991455078125,"other":"shape2","detail":"Cube.006"},{"actutorId":156,"timestamp":467.05999755859377,"duration":0.399993896484375,"other":"shape2","detail":"Cube.017"},{"actutorId":165,"timestamp":467.17999267578127,"duration":0.540008544921875,"other":"shape2","detail":"Cube.017"},{"actutorId":78,"timestamp":467.17999267578127,"duration":0.29998779296875,"other":"shape2","detail":"Cube.006"},{"actutorId":64,"timestamp":467.16998291015627,"duration":0.339996337890625,"other":"shape2","detail":"Cube.006"},{"actutorId":77,"timestamp":467.0999755859375,"duration":0.510009765625,"other":"shape2","detail":"Cube.006"},{"actutorId":164,"timestamp":467.1099853515625,"duration":0.5,"other":"shape2","detail":"Cube.017"},{"actutorId":165,"timestamp":467.17999267578127,"duration":0.540008544921875,"other":"shape2","detail":"Cube.017"},{"actutorId":110,"timestamp":467.0099792480469,"duration":0.80999755859375,"other":"shape2","detail":"Cube.006"},{"actutorId":65,"timestamp":467.1099853515625,"duration":0.769989013671875,"other":"shape2","detail":"Cube.006"},{"actutorId":101,"timestamp":466.5299987792969,"duration":1.399993896484375,"other":"shape2","detail":"Cube.006"},{"actutorId":69,"timestamp":466.5699768066406,"duration":1.3800048828125,"other":"shape2","detail":"Cube.006"},{"actutorId":70,"timestamp":466.53997802734377,"duration":1.410003662109375,"other":"shape2","detail":"Cube.006"},{"actutorId":103,"timestamp":466.5799865722656,"duration":1.3699951171875,"other":"shape2","detail":"Cube.006"},{"actutorId":102,"timestamp":466.55999755859377,"duration":1.389984130859375,"other":"shape2","detail":"Cube.006"},{"actutorId":68,"timestamp":466.5999755859375,"duration":1.360015869140625,"other":"shape2","detail":"Cube.006"},{"actutorId":104,"timestamp":466.5999755859375,"duration":1.360015869140625,"other":"shape2","detail":"Cube.006"},{"actutorId":100,"timestamp":466.55999755859377,"duration":1.399993896484375,"other":"shape2","detail":"Cube.006"},{"actutorId":67,"timestamp":466.6999816894531,"duration":1.279998779296875,"other":"shape2","detail":"Cube.006"},{"actutorId":71,"timestamp":466.5699768066406,"duration":1.410003662109375,"other":"shape2","detail":"Cube.006"},{"actutorId":105,"timestamp":466.6299743652344,"duration":1.350006103515625,"other":"shape2","detail":"Cube.006"},{"actutorId":99,"timestamp":466.5999755859375,"duration":1.3800048828125,"other":"shape2","detail":"Cube.006"},{"actutorId":106,"timestamp":466.6499938964844,"duration":1.339996337890625,"other":"shape2","detail":"Cube.006"},{"actutorId":66,"timestamp":467.0799865722656,"duration":0.910003662109375,"other":"shape2","detail":"Cube.006"},{"actutorId":72,"timestamp":466.6199951171875,"duration":1.3699951171875,"other":"shape2","detail":"Cube.006"},{"actutorId":98,"timestamp":466.6299743652344,"duration":1.370025634765625,"other":"shape2","detail":"Cube.006"},{"actutorId":107,"timestamp":466.67999267578127,"duration":1.32000732421875,"other":"shape2","detail":"Cube.006"},{"actutorId":73,"timestamp":466.6499938964844,"duration":1.3599853515625,"other":"shape2","detail":"Cube.006"},{"actutorId":97,"timestamp":466.66998291015627,"duration":1.339996337890625,"other":"shape2","detail":"Cube.006"},{"actutorId":109,"timestamp":466.72998046875,"duration":1.279998779296875,"other":"shape2","detail":"Cube.006"},{"actutorId":108,"timestamp":466.6999816894531,"duration":1.30999755859375,"other":"shape2","detail":"Cube.006"},{"actutorId":96,"timestamp":466.6999816894531,"duration":1.33001708984375,"other":"shape2","detail":"Cube.006"},{"actutorId":75,"timestamp":466.72998046875,"duration":1.30999755859375,"other":"shape2","detail":"Cube.006"},{"actutorId":74,"timestamp":466.6999816894531,"duration":1.339996337890625,"other":"shape2","detail":"Cube.006"},{"actutorId":76,"timestamp":466.9700012207031,"duration":1.079986572265625,"other":"shape2","detail":"Cube.006"},{"actutorId":95,"timestamp":466.739990234375,"duration":1.30999755859375,"other":"shape2","detail":"Cube.006"},{"actutorId":94,"timestamp":466.7799987792969,"duration":1.30999755859375,"other":"shape2","detail":"Cube.006"},{"actutorId":93,"timestamp":466.79998779296877,"duration":1.29998779296875,"other":"shape2","detail":"Cube.006"},{"actutorId":92,"timestamp":466.8199768066406,"duration":1.290008544921875,"other":"shape2","detail":"Cube.006"},{"actutorId":91,"timestamp":466.8299865722656,"duration":1.290008544921875,"other":"shape2","detail":"Cube.006"},{"actutorId":91,"timestamp":472.8899841308594,"duration":0.08001708984375,"other":"shape3","detail":"Cube.006"},{"actutorId":72,"timestamp":472.8899841308594,"duration":0.220001220703125,"other":"shape3","detail":"Cube.006"},{"actutorId":102,"timestamp":472.8699951171875,"duration":0.29998779296875,"other":"shape3","detail":"Cube.006"},{"actutorId":71,"timestamp":472.78997802734377,"duration":0.4000244140625,"other":"shape3","detail":"Cube.006"},{"actutorId":101,"timestamp":472.7799987792969,"duration":0.470001220703125,"other":"shape3","detail":"Cube.006"},{"actutorId":95,"timestamp":472.80999755859377,"duration":0.470001220703125,"other":"shape3","detail":"Cube.006"},{"actutorId":101,"timestamp":473.3599853515625,"duration":0.019989013671875,"other":"shape3","detail":"Cube.006"},{"actutorId":92,"timestamp":472.8599853515625,"duration":0.6400146484375,"other":"shape3","detail":"Cube.006"},{"actutorId":94,"timestamp":472.8199768066406,"duration":0.75,"other":"shape3","detail":"Cube.006"},{"actutorId":93,"timestamp":472.8499755859375,"duration":0.82000732421875,"other":"shape3","detail":"Cube.006"},{"actutorId":101,"timestamp":473.8199768066406,"duration":0.1400146484375,"other":"shape3","detail":"Cube.006"},{"actutorId":102,"timestamp":473.8799743652344,"duration":0.100006103515625,"other":"shape3","detail":"Cube.006"},{"actutorId":70,"timestamp":473.92999267578127,"duration":0.04998779296875,"other":"shape3","detail":"Cube.006"},{"actutorId":103,"timestamp":473.9100036621094,"duration":0.079986572265625,"other":"shape3","detail":"Cube.006"},{"actutorId":100,"timestamp":472.6399841308594,"duration":1.350006103515625,"other":"shape3","detail":"Cube.006"},{"actutorId":71,"timestamp":473.8599853515625,"duration":0.1400146484375,"other":"shape3","detail":"Cube.006"},{"actutorId":104,"timestamp":473.9599914550781,"duration":0.040008544921875,"other":"shape3","detail":"Cube.006"},{"actutorId":99,"timestamp":472.6600036621094,"duration":1.3599853515625,"other":"shape3","detail":"Cube.006"},{"actutorId":105,"timestamp":474.0,"duration":0.019989013671875,"other":"shape3","detail":"Cube.006"},{"actutorId":72,"timestamp":473.8899841308594,"duration":0.1400146484375,"other":"shape3","detail":"Cube.006"},{"actutorId":98,"timestamp":472.67999267578127,"duration":1.350006103515625,"other":"shape3","detail":"Cube.006"},{"actutorId":97,"timestamp":472.7099914550781,"duration":1.350006103515625,"other":"shape3","detail":"Cube.006"},{"actutorId":73,"timestamp":473.9499816894531,"duration":0.110015869140625,"other":"shape3","detail":"Cube.006"},{"actutorId":96,"timestamp":472.75,"duration":1.329986572265625,"other":"shape3","detail":"Cube.006"},{"actutorId":74,"timestamp":474.0199890136719,"duration":0.07000732421875,"other":"shape3","detail":"Cube.006"},{"actutorId":95,"timestamp":473.8799743652344,"duration":0.220001220703125,"other":"shape3","detail":"Cube.006"},{"actutorId":94,"timestamp":473.8199768066406,"duration":0.30999755859375,"other":"shape3","detail":"Cube.006"},{"actutorId":93,"timestamp":473.7799987792969,"duration":0.3599853515625,"other":"shape3","detail":"Cube.006"},{"actutorId":92,"timestamp":473.8599853515625,"duration":0.300018310546875,"other":"shape3","detail":"Cube.006"},{"actutorId":91,"timestamp":473.91998291015627,"duration":0.240020751953125,"other":"shape3","detail":"Cube.006"},{"actutorId":151,"timestamp":480.1499938964844,"duration":0.019989013671875,"other":"shape4","detail":"Cube.006"},{"actutorId":77,"timestamp":480.2599792480469,"duration":0.1500244140625,"other":"shape4","detail":"Cube.017"},{"actutorId":64,"timestamp":480.1999816894531,"duration":0.260009765625,"other":"shape4","detail":"Cube.017"},{"actutorId":65,"timestamp":480.1999816894531,"duration":0.260009765625,"other":"shape4","detail":"Cube.017"},{"actutorId":136,"timestamp":480.3599853515625,"duration":0.1199951171875,"other":"shape4","detail":"Cube.006"},{"actutorId":76,"timestamp":480.3599853515625,"duration":0.1199951171875,"other":"shape4","detail":"Cube.017"},{"actutorId":67,"timestamp":480.4599914550781,"duration":0.529998779296875,"other":"shape4","detail":"Cube.017"},{"actutorId":152,"timestamp":480.1299743652344,"duration":0.490020751953125,"other":"shape4","detail":"Cube.006"},{"actutorId":166,"timestamp":480.1999816894531,"duration":0.45001220703125,"other":"shape4","detail":"Cube.006"},{"actutorId":128,"timestamp":480.16998291015627,"duration":0.480010986328125,"other":"shape4","detail":"Cube.006"},{"actutorId":134,"timestamp":480.16998291015627,"duration":0.510009765625,"other":"shape4","detail":"Cube.006"},{"actutorId":106,"timestamp":480.5699768066406,"duration":0.529998779296875,"other":"shape4","detail":"Cube.015"},{"actutorId":75,"timestamp":480.5299987792969,"duration":0.319976806640625,"other":"shape4","detail":"Cube.015"},{"actutorId":75,"timestamp":480.5299987792969,"duration":0.319976806640625,"other":"shape4","detail":"Cube.015"},{"actutorId":103,"timestamp":480.47998046875,"duration":0.3699951171875,"other":"shape4","detail":"Cube.017"},{"actutorId":97,"timestamp":480.5099792480469,"duration":0.3699951171875,"other":"shape4","detail":"Cube.017"},{"actutorId":66,"timestamp":480.47998046875,"duration":0.6199951171875,"other":"shape4","detail":"Cube.015"},{"actutorId":67,"timestamp":480.4599914550781,"duration":0.529998779296875,"other":"shape4","detail":"Cube.017"},{"actutorId":105,"timestamp":480.3799743652344,"duration":0.920013427734375,"other":"shape4","detail":"Cube.017"},{"actutorId":94,"timestamp":480.44000244140627,"duration":0.54998779296875,"other":"shape4","detail":"Cube.017"},{"actutorId":95,"timestamp":480.3599853515625,"duration":0.660003662109375,"other":"shape4","detail":"Cube.017"},{"actutorId":96,"timestamp":480.3399963378906,"duration":0.709991455078125,"other":"shape4","detail":"Cube.017"},{"actutorId":107,"timestamp":480.2699890136719,"duration":0.80999755859375,"other":"shape4","detail":"Cube.017"},{"actutorId":106,"timestamp":480.5699768066406,"duration":0.529998779296875,"other":"shape4","detail":"Cube.015"},{"actutorId":66,"timestamp":480.47998046875,"duration":0.6199951171875,"other":"shape4","detail":"Cube.015"},{"actutorId":66,"timestamp":480.47998046875,"duration":0.6199951171875,"other":"shape4","detail":"Cube.015"},{"actutorId":64,"timestamp":480.989990234375,"duration":0.339996337890625,"other":"shape4","detail":"Cube.017"},{"actutorId":106,"timestamp":480.5699768066406,"duration":0.529998779296875,"other":"shape4","detail":"Cube.015"},{"actutorId":104,"timestamp":480.16998291015627,"duration":0.959991455078125,"other":"shape4","detail":"Cube.017"},{"actutorId":76,"timestamp":480.9100036621094,"duration":0.449981689453125,"other":"shape4","detail":"Cube.017"},{"actutorId":65,"timestamp":480.92999267578127,"duration":0.3699951171875,"other":"shape4","detail":"Cube.017"},{"actutorId":105,"timestamp":480.3799743652344,"duration":0.920013427734375,"other":"shape4","detail":"Cube.017"},{"actutorId":65,"timestamp":480.92999267578127,"duration":0.3699951171875,"other":"shape4","detail":"Cube.017"},{"actutorId":65,"timestamp":480.92999267578127,"duration":0.3699951171875,"other":"shape4","detail":"Cube.017"},{"actutorId":64,"timestamp":480.989990234375,"duration":0.339996337890625,"other":"shape4","detail":"Cube.017"},{"actutorId":133,"timestamp":480.0099792480469,"duration":1.350006103515625,"other":"shape4","detail":"Cube.006"},{"actutorId":132,"timestamp":479.97998046875,"duration":1.3800048828125,"other":"shape4","detail":"Cube.006"},{"actutorId":131,"timestamp":479.9700012207031,"duration":1.389984130859375,"other":"shape4","detail":"Cube.006"},{"actutorId":160,"timestamp":479.97998046875,"duration":1.3800048828125,"other":"shape4","detail":"Cube.006"},{"actutorId":77,"timestamp":480.9599914550781,"duration":0.399993896484375,"other":"shape4","detail":"Cube.017"},{"actutorId":76,"timestamp":480.9100036621094,"duration":0.449981689453125,"other":"shape4","detail":"Cube.017"},{"actutorId":76,"timestamp":480.9100036621094,"duration":0.449981689453125,"other":"shape4","detail":"Cube.017"},{"actutorId":130,"timestamp":480.0,"duration":1.389984130859375,"other":"shape4","detail":"Cube.006"},{"actutorId":134,"timestamp":481.239990234375,"duration":0.149993896484375,"other":"shape4","detail":"Cube.006"},{"actutorId":158,"timestamp":480.0299987792969,"duration":1.3599853515625,"other":"shape4","detail":"Cube.006"},{"actutorId":159,"timestamp":480.0,"duration":1.389984130859375,"other":"shape4","detail":"Cube.006"},{"actutorId":128,"timestamp":481.2699890136719,"duration":0.149993896484375,"other":"shape4","detail":"Cube.006"},{"actutorId":129,"timestamp":480.0299987792969,"duration":1.389984130859375,"other":"shape4","detail":"Cube.006"},{"actutorId":161,"timestamp":480.0099792480469,"duration":1.410003662109375,"other":"shape4","detail":"Cube.006"},{"actutorId":162,"timestamp":480.03997802734377,"duration":1.3800048828125,"other":"shape4","detail":"Cube.006"},{"actutorId":156,"timestamp":480.0699768066406,"duration":1.350006103515625,"other":"shape4","detail":"Cube.006"},{"actutorId":157,"timestamp":480.03997802734377,"duration":1.3800048828125,"other":"shape4","detail":"Cube.006"},{"actutorId":153,"timestamp":480.1199951171875,"duration":1.32000732421875,"other":"shape4","detail":"Cube.006"},{"actutorId":155,"timestamp":480.1099853515625,"duration":1.33001708984375,"other":"shape4","detail":"Cube.006"},{"actutorId":163,"timestamp":480.0799865722656,"duration":1.360015869140625,"other":"shape4","detail":"Cube.006"},{"actutorId":152,"timestamp":480.7599792480469,"duration":0.680023193359375,"other":"shape4","detail":"Cube.006"},{"actutorId":164,"timestamp":480.1099853515625,"duration":1.360015869140625,"other":"shape4","detail":"Cube.006"},{"actutorId":154,"timestamp":480.1199951171875,"duration":1.350006103515625,"other":"shape4","detail":"Cube.006"},{"actutorId":165,"timestamp":480.1299743652344,"duration":1.360015869140625,"other":"shape4","detail":"Cube.006"},{"actutorId":166,"timestamp":481.29998779296877,"duration":0.19000244140625,"other":"shape4","detail":"Cube.006"},{"actutorId":75,"timestamp":486.1499938964844,"duration":0.30999755859375,"other":"shape5","detail":"Cube.017"},{"actutorId":74,"timestamp":486.3999938964844,"duration":0.19000244140625,"other":"shape5","detail":"Cube.017"},{"actutorId":96,"timestamp":486.3199768066406,"duration":0.33001708984375,"other":"shape5","detail":"Cube.017"},{"actutorId":95,"timestamp":486.22998046875,"duration":0.420013427734375,"other":"shape5","detail":"Cube.017"},{"actutorId":158,"timestamp":486.28997802734377,"duration":1.089996337890625,"other":"shape5","detail":"Cube.006"},{"actutorId":159,"timestamp":486.2599792480469,"duration":1.1199951171875,"other":"shape5","detail":"Cube.006"},{"actutorId":160,"timestamp":486.22998046875,"duration":1.149993896484375,"other":"shape5","detail":"Cube.006"},{"actutorId":161,"timestamp":486.3399963378906,"duration":1.07000732421875,"other":"shape5","detail":"Cube.006"},{"actutorId":162,"timestamp":486.92999267578127,"duration":0.480010986328125,"other":"shape5","detail":"Cube.006"},{"actutorId":156,"timestamp":487.0699768066406,"duration":0.34002685546875,"other":"shape5","detail":"Cube.006"},{"actutorId":157,"timestamp":486.3199768066406,"duration":1.09002685546875,"other":"shape5","detail":"Cube.006"},{"actutorId":163,"timestamp":487.3799743652344,"duration":0.060028076171875,"other":"shape5","detail":"Cube.006"},{"actutorId":139,"timestamp":491.239990234375,"duration":0.029998779296875,"other":"shape6","detail":"Cube.051"},{"actutorId":140,"timestamp":491.28997802734377,"duration":0.029998779296875,"other":"shape6","detail":"Cube.047"},{"actutorId":107,"timestamp":491.2699890136719,"duration":0.660003662109375,"other":"shape6","detail":"Cube.020"},{"actutorId":107,"timestamp":491.2699890136719,"duration":0.660003662109375,"other":"shape6","detail":"Cube.020"},{"actutorId":69,"timestamp":491.1199951171875,"duration":0.259979248046875,"other":"shape6","detail":"Cube.020"},{"actutorId":108,"timestamp":491.17999267578127,"duration":0.279998779296875,"other":"shape6","detail":"Cube.036"},{"actutorId":95,"timestamp":491.2699890136719,"duration":0.660003662109375,"other":"shape6","detail":"Cube.020"},{"actutorId":140,"timestamp":491.4100036621094,"duration":0.689971923828125,"other":"shape6","detail":"Cube.047"},{"actutorId":94,"timestamp":491.1499938964844,"duration":0.850006103515625,"other":"shape6","detail":"Cube.020"},{"actutorId":94,"timestamp":491.1499938964844,"duration":0.850006103515625,"other":"shape6","detail":"Cube.020"},{"actutorId":139,"timestamp":491.54998779296877,"duration":0.029998779296875,"other":"shape6","detail":"Cube.011"},{"actutorId":93,"timestamp":491.0699768066406,"duration":0.529998779296875,"other":"shape6","detail":"Cube.036"},{"actutorId":98,"timestamp":491.5799865722656,"duration":0.610015869140625,"other":"shape6","detail":"Cube.020"},{"actutorId":107,"timestamp":491.2699890136719,"duration":0.660003662109375,"other":"shape6","detail":"Cube.020"},{"actutorId":108,"timestamp":491.739990234375,"duration":0.139984130859375,"other":"shape6","detail":"Cube.020"},{"actutorId":108,"timestamp":491.739990234375,"duration":0.139984130859375,"other":"shape6","detail":"Cube.020"},{"actutorId":70,"timestamp":491.03997802734377,"duration":0.760009765625,"other":"shape6","detail":"Cube.020"},{"actutorId":109,"timestamp":491.5999755859375,"duration":0.20001220703125,"other":"shape6","detail":"Cube.036"},{"actutorId":94,"timestamp":491.1499938964844,"duration":0.850006103515625,"other":"shape6","detail":"Cube.020"},{"actutorId":71,"timestamp":491.0099792480469,"duration":0.80999755859375,"other":"shape6","detail":"Cube.020"},{"actutorId":108,"timestamp":491.739990234375,"duration":0.139984130859375,"other":"shape6","detail":"Cube.020"},{"actutorId":121,"timestamp":491.69000244140627,"duration":0.209991455078125,"other":"shape6","detail":"Cube.051"},{"actutorId":108,"timestamp":491.739990234375,"duration":0.139984130859375,"other":"shape6","detail":"Cube.020"},{"actutorId":106,"timestamp":490.92999267578127,"duration":0.970001220703125,"other":"shape6","detail":"Cube.020"},{"actutorId":121,"timestamp":491.69000244140627,"duration":0.209991455078125,"other":"shape6","detail":"Cube.051"},{"actutorId":93,"timestamp":491.69000244140627,"duration":0.209991455078125,"other":"shape6","detail":"Cube.034"},{"actutorId":93,"timestamp":491.69000244140627,"duration":0.209991455078125,"other":"shape6","detail":"Cube.034"},{"actutorId":93,"timestamp":491.69000244140627,"duration":0.209991455078125,"other":"shape6","detail":"Cube.034"},{"actutorId":107,"timestamp":491.2699890136719,"duration":0.660003662109375,"other":"shape6","detail":"Cube.020"},{"actutorId":95,"timestamp":491.2699890136719,"duration":0.660003662109375,"other":"shape6","detail":"Cube.020"},{"actutorId":140,"timestamp":491.4100036621094,"duration":0.689971923828125,"other":"shape6","detail":"Cube.047"},{"actutorId":92,"timestamp":491.5999755859375,"duration":0.370025634765625,"other":"shape6","detail":"Cube.036"},{"actutorId":122,"timestamp":491.6499938964844,"duration":0.41998291015625,"other":"shape6","detail":"Cube.051"},{"actutorId":105,"timestamp":490.8999938964844,"duration":1.100006103515625,"other":"shape6","detail":"Cube.020"},{"actutorId":123,"timestamp":491.7699890136719,"duration":0.279998779296875,"other":"shape6","detail":"Cube.049"},{"actutorId":124,"timestamp":491.8999938964844,"duration":0.100006103515625,"other":"shape6","detail":"Cube.011"},{"actutorId":94,"timestamp":491.1499938964844,"duration":0.850006103515625,"other":"shape6","detail":"Cube.020"},{"actutorId":138,"timestamp":491.79998779296877,"duration":0.20001220703125,"other":"shape6","detail":"Cube.016"},{"actutorId":123,"timestamp":491.7699890136719,"duration":0.279998779296875,"other":"shape6","detail":"Cube.049"},{"actutorId":104,"timestamp":490.8699951171875,"duration":1.17999267578125,"other":"shape6","detail":"Cube.020"},{"actutorId":139,"timestamp":491.7099914550781,"duration":0.70001220703125,"other":"shape6","detail":"Cube.047"},{"actutorId":96,"timestamp":490.92999267578127,"duration":1.139984130859375,"other":"shape6","detail":"Cube.020"},{"actutorId":122,"timestamp":491.6499938964844,"duration":0.41998291015625,"other":"shape6","detail":"Cube.051"},{"actutorId":140,"timestamp":491.4100036621094,"duration":0.689971923828125,"other":"shape6","detail":"Cube.047"},{"actutorId":138,"timestamp":492.0699768066406,"duration":0.34002685546875,"other":"shape6","detail":"Cube.049"},{"actutorId":103,"timestamp":490.8699951171875,"duration":1.259979248046875,"other":"shape6","detail":"Cube.020"},{"actutorId":101,"timestamp":490.8199768066406,"duration":1.34002685546875,"other":"shape6","detail":"Cube.020"},{"actutorId":97,"timestamp":490.8999938964844,"duration":1.260009765625,"other":"shape6","detail":"Cube.020"},{"actutorId":102,"timestamp":490.8399963378906,"duration":1.350006103515625,"other":"shape6","detail":"Cube.020"},{"actutorId":98,"timestamp":491.5799865722656,"duration":0.610015869140625,"other":"shape6","detail":"Cube.020"},{"actutorId":100,"timestamp":490.8399963378906,"duration":1.350006103515625,"other":"shape6","detail":"Cube.020"},{"actutorId":134,"timestamp":492.1600036621094,"duration":0.219970703125,"other":"shape6","detail":"Cube.011"},{"actutorId":99,"timestamp":490.8699951171875,"duration":1.339996337890625,"other":"shape6","detail":"Cube.020"},{"actutorId":133,"timestamp":492.2099914550781,"duration":0.1199951171875,"other":"shape6","detail":"Cube.050"},{"actutorId":152,"timestamp":492.1299743652344,"duration":0.1400146484375,"other":"shape6","detail":"Cube.051"},{"actutorId":154,"timestamp":492.2699890136719,"duration":0.019989013671875,"other":"shape6","detail":"Cube.049"},{"actutorId":154,"timestamp":492.2699890136719,"duration":0.019989013671875,"other":"shape6","detail":"Cube.049"},{"actutorId":133,"timestamp":492.2099914550781,"duration":0.1199951171875,"other":"shape6","detail":"Cube.050"},{"actutorId":134,"timestamp":492.1600036621094,"duration":0.219970703125,"other":"shape6","detail":"Cube.011"},{"actutorId":139,"timestamp":491.7099914550781,"duration":0.70001220703125,"other":"shape6","detail":"Cube.047"},{"actutorId":139,"timestamp":491.7099914550781,"duration":0.70001220703125,"other":"shape6","detail":"Cube.047"},{"actutorId":138,"timestamp":492.0699768066406,"duration":0.34002685546875,"other":"shape6","detail":"Cube.049"},{"actutorId":138,"timestamp":492.0699768066406,"duration":0.34002685546875,"other":"shape6","detail":"Cube.049"},{"actutorId":137,"timestamp":491.9700012207031,"duration":0.44000244140625,"other":"shape6","detail":"Cube.011"},{"actutorId":135,"timestamp":492.0299987792969,"duration":0.3800048828125,"other":"shape6","detail":"Cube.011"},{"actutorId":153,"timestamp":492.19000244140627,"duration":0.25,"other":"shape6","detail":"Cube.051"},{"actutorId":153,"timestamp":492.19000244140627,"duration":0.25,"other":"shape6","detail":"Cube.051"},{"actutorId":168,"timestamp":497.1600036621094,"duration":0.189971923828125,"other":"shape7","detail":"Cube.014"},{"actutorId":168,"timestamp":497.5199890136719,"duration":0.540008544921875,"other":"shape7","detail":"Cube.014"},{"actutorId":168,"timestamp":503.6299743652344,"duration":0.110015869140625,"other":"shape8","detail":"Cube.010"},{"actutorId":169,"timestamp":503.5899963378906,"duration":0.199981689453125,"other":"shape8","detail":"Cube.010"},{"actutorId":170,"timestamp":503.53997802734377,"duration":0.550018310546875,"other":"shape8","detail":"Cube.010"},{"actutorId":80,"timestamp":504.04998779296877,"duration":0.360015869140625,"other":"shape8","detail":"Cube.008"},{"actutorId":170,"timestamp":504.25,"duration":0.239990234375,"other":"shape8","detail":"Cube.010"},{"actutorId":169,"timestamp":504.3599853515625,"duration":0.149993896484375,"other":"shape8","detail":"Cube.010"},{"actutorId":78,"timestamp":509.1099853515625,"duration":0.980010986328125,"other":"shape9","detail":"Cube.008"},{"actutorId":80,"timestamp":509.0999755859375,"duration":1.279998779296875,"other":"shape9","detail":"Cube.008"},{"actutorId":79,"timestamp":509.0999755859375,"duration":1.279998779296875,"other":"shape9","detail":"Cube.008"},{"actutorId":168,"timestamp":509.17999267578127,"duration":1.279998779296875,"other":"shape9","detail":"Cube.010"},{"actutorId":170,"timestamp":509.16998291015627,"duration":1.290008544921875,"other":"shape9","detail":"Cube.010"},{"actutorId":169,"timestamp":509.16998291015627,"duration":1.290008544921875,"other":"shape9","detail":"Cube.010"},{"actutorId":168,"timestamp":516.3800048828125,"duration":0.0999755859375,"other":"shape10","detail":"Cube.008"},{"actutorId":169,"timestamp":516.3599853515625,"duration":0.1500244140625,"other":"shape10","detail":"Cube.008"},{"actutorId":170,"timestamp":516.3599853515625,"duration":0.1500244140625,"other":"shape10","detail":"Cube.008"},{"actutorId":163,"timestamp":516.6499633789063,"duration":0.05999755859375,"other":"shape10","detail":"Cube.011"},{"actutorId":165,"timestamp":516.5800170898438,"duration":0.219970703125,"other":"shape10","detail":"Cube.011"},{"actutorId":164,"timestamp":516.5700073242188,"duration":0.260009765625,"other":"shape10","detail":"Cube.011"},{"actutorId":170,"timestamp":517.010009765625,"duration":0.00994873046875,"other":"shape10","detail":"Cube.008"},{"actutorId":170,"timestamp":517.0299682617188,"duration":0.08001708984375,"other":"shape10","detail":"Cube.008"},{"actutorId":109,"timestamp":528.47998046875,"duration":0.030029296875,"other":"shape12","detail":"Cube.011"},{"actutorId":68,"timestamp":528.469970703125,"duration":0.239990234375,"other":"shape12","detail":"Cube.010"},{"actutorId":69,"timestamp":528.469970703125,"duration":0.57000732421875,"other":"shape12","detail":"Cube.010"},{"actutorId":70,"timestamp":528.469970703125,"duration":0.73004150390625,"other":"shape12","detail":"Cube.010"},{"actutorId":110,"timestamp":528.4500122070313,"duration":1.05999755859375,"other":"shape12","detail":"Cube.047"},{"actutorId":109,"timestamp":529.2099609375,"duration":0.1600341796875,"other":"shape12","detail":"Cube.049"},{"actutorId":108,"timestamp":529.3800048828125,"duration":0.0799560546875,"other":"shape12","detail":"Cube.011"},{"actutorId":92,"timestamp":529.3800048828125,"duration":0.1199951171875,"other":"shape12","detail":"Cube.047"},{"actutorId":92,"timestamp":529.3800048828125,"duration":0.1199951171875,"other":"shape12","detail":"Cube.047"},{"actutorId":110,"timestamp":528.4500122070313,"duration":1.05999755859375,"other":"shape12","detail":"Cube.047"},{"actutorId":62,"timestamp":529.3800048828125,"duration":0.219970703125,"other":"shape12","detail":"Cube.051"},{"actutorId":96,"timestamp":529.5,"duration":0.1400146484375,"other":"shape12","detail":"Cube.050"},{"actutorId":95,"timestamp":529.47998046875,"duration":0.1600341796875,"other":"shape12","detail":"Cube.011"},{"actutorId":107,"timestamp":529.4500122070313,"duration":0.3699951171875,"other":"shape12","detail":"Cube.011"},{"actutorId":64,"timestamp":529.4199829101563,"duration":0.260009765625,"other":"shape12","detail":"Cube.011"},{"actutorId":108,"timestamp":529.6499633789063,"duration":0.1600341796875,"other":"shape12","detail":"Cube.016"},{"actutorId":94,"timestamp":529.4199829101563,"duration":0.47003173828125,"other":"shape12","detail":"Cube.011"},{"actutorId":108,"timestamp":529.6499633789063,"duration":0.1600341796875,"other":"shape12","detail":"Cube.016"},{"actutorId":107,"timestamp":529.4500122070313,"duration":0.3699951171875,"other":"shape12","detail":"Cube.011"},{"actutorId":93,"timestamp":529.3800048828125,"duration":0.510009765625,"other":"shape12","detail":"Cube.051"},{"actutorId":62,"timestamp":529.719970703125,"duration":0.0400390625,"other":"shape12","detail":"Cube.051"},{"actutorId":63,"timestamp":529.2899780273438,"duration":0.489990234375,"other":"shape12","detail":"Cube.011"},{"actutorId":63,"timestamp":529.2899780273438,"duration":0.489990234375,"other":"shape12","detail":"Cube.011"},{"actutorId":110,"timestamp":529.6099853515625,"duration":0.16998291015625,"other":"shape12","detail":"Cube.047"},{"actutorId":109,"timestamp":529.7099609375,"duration":0.09002685546875,"other":"shape12","detail":"Cube.047"},{"actutorId":109,"timestamp":529.7099609375,"duration":0.09002685546875,"other":"shape12","detail":"Cube.047"},{"actutorId":109,"timestamp":529.7099609375,"duration":0.09002685546875,"other":"shape12","detail":"Cube.047"},{"actutorId":108,"timestamp":529.6499633789063,"duration":0.1600341796875,"other":"shape12","detail":"Cube.016"},{"actutorId":108,"timestamp":529.6499633789063,"duration":0.1600341796875,"other":"shape12","detail":"Cube.016"},{"actutorId":108,"timestamp":529.6499633789063,"duration":0.1600341796875,"other":"shape12","detail":"Cube.016"},{"actutorId":107,"timestamp":529.4500122070313,"duration":0.3699951171875,"other":"shape12","detail":"Cube.011"},{"actutorId":94,"timestamp":529.4199829101563,"duration":0.47003173828125,"other":"shape12","detail":"Cube.011"},{"actutorId":92,"timestamp":529.6499633789063,"duration":0.24005126953125,"other":"shape12","detail":"Cube.047"},{"actutorId":93,"timestamp":529.3800048828125,"duration":0.510009765625,"other":"shape12","detail":"Cube.051"},{"actutorId":94,"timestamp":529.4199829101563,"duration":0.47003173828125,"other":"shape12","detail":"Cube.011"},{"actutorId":92,"timestamp":529.6499633789063,"duration":0.24005126953125,"other":"shape12","detail":"Cube.047"},{"actutorId":93,"timestamp":529.3800048828125,"duration":0.510009765625,"other":"shape12","detail":"Cube.051"},{"actutorId":71,"timestamp":534.3999633789063,"duration":0.0400390625,"other":"shape13","detail":"Cube.010"},{"actutorId":98,"timestamp":534.469970703125,"duration":0.3699951171875,"other":"shape13","detail":"Cube.010"},{"actutorId":98,"timestamp":534.8800048828125,"duration":0.01995849609375,"other":"shape13","detail":"Cube.010"},{"actutorId":100,"timestamp":534.4099731445313,"duration":0.5400390625,"other":"shape13","detail":"Cube.010"},{"actutorId":99,"timestamp":534.4400024414063,"duration":0.510009765625,"other":"shape13","detail":"Cube.010"},{"actutorId":97,"timestamp":534.5,"duration":0.469970703125,"other":"shape13","detail":"Cube.010"},{"actutorId":99,"timestamp":535.1199951171875,"duration":0.14996337890625,"other":"shape13","detail":"Cube.010"},{"actutorId":100,"timestamp":535.0999755859375,"duration":0.20001220703125,"other":"shape13","detail":"Cube.010"},{"actutorId":157,"timestamp":539.1900024414063,"duration":0.29998779296875,"other":"shape14","detail":"Cube.011"},{"actutorId":162,"timestamp":539.1900024414063,"duration":0.1099853515625,"other":"shape14","detail":"Cube.007"},{"actutorId":163,"timestamp":539.219970703125,"duration":0.05999755859375,"other":"shape14","detail":"Cube.007"},{"actutorId":155,"timestamp":539.260009765625,"duration":0.03997802734375,"other":"shape14","detail":"Cube.011"},{"actutorId":162,"timestamp":539.1900024414063,"duration":0.1099853515625,"other":"shape14","detail":"Cube.007"},{"actutorId":161,"timestamp":539.1300048828125,"duration":0.2099609375,"other":"shape14","detail":"Cube.007"},{"actutorId":156,"timestamp":539.219970703125,"duration":0.21002197265625,"other":"shape14","detail":"Cube.011"},{"actutorId":159,"timestamp":539.1300048828125,"duration":0.3499755859375,"other":"shape14","detail":"Cube.007"},{"actutorId":153,"timestamp":539.3800048828125,"duration":0.1300048828125,"other":"shape14","detail":"Cube.011"},{"actutorId":160,"timestamp":539.0999755859375,"duration":0.35003662109375,"other":"shape14","detail":"Cube.007"},{"actutorId":152,"timestamp":539.2799682617188,"duration":0.1700439453125,"other":"shape14","detail":"Cube.011"},{"actutorId":152,"timestamp":539.2799682617188,"duration":0.1700439453125,"other":"shape14","detail":"Cube.011"},{"actutorId":154,"timestamp":539.2799682617188,"duration":0.19000244140625,"other":"shape14","detail":"Cube.011"},{"actutorId":158,"timestamp":539.1599731445313,"duration":0.35003662109375,"other":"shape14","detail":"Cube.007"},{"actutorId":159,"timestamp":539.1300048828125,"duration":0.3499755859375,"other":"shape14","detail":"Cube.007"},{"actutorId":157,"timestamp":539.1900024414063,"duration":0.29998779296875,"other":"shape14","detail":"Cube.011"},{"actutorId":153,"timestamp":539.3800048828125,"duration":0.1300048828125,"other":"shape14","detail":"Cube.011"},{"actutorId":158,"timestamp":539.1599731445313,"duration":0.35003662109375,"other":"shape14","detail":"Cube.007"},{"actutorId":161,"timestamp":540.2899780273438,"duration":0.1400146484375,"other":"shape14","detail":"Cube.007"},{"actutorId":160,"timestamp":539.9299926757813,"duration":0.52996826171875,"other":"shape14","detail":"Cube.007"},{"actutorId":157,"timestamp":540.25,"duration":0.219970703125,"other":"shape14","detail":"Cube.011"},{"actutorId":159,"timestamp":540.1900024414063,"duration":0.27996826171875,"other":"shape14","detail":"Cube.011"},{"actutorId":159,"timestamp":540.1900024414063,"duration":0.27996826171875,"other":"shape14","detail":"Cube.011"},{"actutorId":158,"timestamp":540.2000122070313,"duration":0.27996826171875,"other":"shape14","detail":"Cube.007"},{"actutorId":158,"timestamp":540.2000122070313,"duration":0.27996826171875,"other":"shape14","detail":"Cube.007"},{"actutorId":75,"timestamp":545.0999755859375,"duration":0.29998779296875,"other":"shape15","detail":"Cube.019"},{"actutorId":74,"timestamp":545.0899658203125,"duration":0.36004638671875,"other":"shape15","detail":"Cube.019"},{"actutorId":72,"timestamp":545.760009765625,"duration":0.0799560546875,"other":"shape15","detail":"Cube.019"},{"actutorId":77,"timestamp":545.7000122070313,"duration":0.40997314453125,"other":"shape15","detail":"Cube.019"},{"actutorId":78,"timestamp":545.719970703125,"duration":0.3900146484375,"other":"shape15","detail":"Cube.019"},{"actutorId":73,"timestamp":545.6400146484375,"duration":0.5899658203125,"other":"shape15","detail":"Cube.019"},{"actutorId":74,"timestamp":545.5399780273438,"duration":0.83001708984375,"other":"shape15","detail":"Cube.019"},{"actutorId":75,"timestamp":545.5700073242188,"duration":0.8299560546875,"other":"shape15","detail":"Cube.019"}]}