{"userId":"user11","date":"09-09-2023-05-48-09","gameName":"OhShape","mode":"PRACTICE","numberOfRounds":1,"numberOfShapes":16,"shapeIndexs":[1,1,4,4,0,0,7,7,3,3,6,6,2,2,5,5],"roundNumber":0,"numberOfCollusions":635,"collusionData":[{"actutorId":75,"timestamp":251.47000122070313,"duration":0.019989013671875,"other":"shape0","detail":"Cube.017"},{"actutorId":106,"timestamp":251.47000122070313,"duration":0.019989013671875,"other":"shape0","detail":"Cube.017"},{"actutorId":75,"timestamp":251.52999877929688,"duration":0.0500030517578125,"other":"shape0","detail":"Cube.017"},{"actutorId":106,"timestamp":251.52999877929688,"duration":0.0500030517578125,"other":"shape0","detail":"Cube.017"},{"actutorId":151,"timestamp":251.75,"duration":0.029998779296875,"other":"shape0","detail":"Cube.006"},{"actutorId":66,"timestamp":251.489990234375,"duration":0.3400115966796875,"other":"shape0","detail":"Cube.017"},{"actutorId":76,"timestamp":251.54998779296876,"duration":0.2800140380859375,"other":"shape0","detail":"Cube.015"},{"actutorId":77,"timestamp":251.5800018310547,"duration":0.29998779296875,"other":"shape0","detail":"Cube.011"},{"actutorId":107,"timestamp":251.87998962402345,"duration":0.029998779296875,"other":"shape0","detail":"Cube.017"},{"actutorId":95,"timestamp":251.87998962402345,"duration":0.029998779296875,"other":"shape0","detail":"Cube.017"},{"actutorId":106,"timestamp":251.6899871826172,"duration":0.260009765625,"other":"shape0","detail":"Cube.017"},{"actutorId":75,"timestamp":251.6599884033203,"duration":0.3100128173828125,"other":"shape0","detail":"Cube.017"},{"actutorId":105,"timestamp":251.54998779296876,"duration":0.420013427734375,"other":"shape0","detail":"Cube.017"},{"actutorId":65,"timestamp":251.47000122070313,"duration":0.5,"other":"shape0","detail":"Cube.011"},{"actutorId":77,"timestamp":251.9099884033203,"duration":0.480010986328125,"other":"shape0","detail":"Cube.017"},{"actutorId":76,"timestamp":251.9499969482422,"duration":0.3000030517578125,"other":"shape0","detail":"Cube.017"},{"actutorId":66,"timestamp":251.9499969482422,"duration":0.25,"other":"shape0","detail":"Cube.017"},{"actutorId":64,"timestamp":251.489990234375,"duration":0.760009765625,"other":"shape0","detail":"Cube.017"},{"actutorId":65,"timestamp":252.1999969482422,"duration":0.0500030517578125,"other":"shape0","detail":"Cube.015"},{"actutorId":65,"timestamp":252.1999969482422,"duration":0.0500030517578125,"other":"shape0","detail":"Cube.015"},{"actutorId":76,"timestamp":251.9499969482422,"duration":0.3000030517578125,"other":"shape0","detail":"Cube.017"},{"actutorId":76,"timestamp":251.9499969482422,"duration":0.3000030517578125,"other":"shape0","detail":"Cube.017"},{"actutorId":64,"timestamp":252.27999877929688,"duration":0.0500030517578125,"other":"shape0","detail":"Cube.017"},{"actutorId":76,"timestamp":252.27999877929688,"duration":0.1100006103515625,"other":"shape0","detail":"Cube.015"},{"actutorId":65,"timestamp":252.27999877929688,"duration":0.0800018310546875,"other":"shape0","detail":"Cube.017"},{"actutorId":78,"timestamp":252.04998779296876,"duration":0.3100128173828125,"other":"shape0","detail":"Cube.017"},{"actutorId":77,"timestamp":251.9099884033203,"duration":0.480010986328125,"other":"shape0","detail":"Cube.017"},{"actutorId":76,"timestamp":252.27999877929688,"duration":0.1100006103515625,"other":"shape0","detail":"Cube.015"},{"actutorId":76,"timestamp":252.4499969482422,"duration":0.0200042724609375,"other":"shape0","detail":"Cube.017"},{"actutorId":65,"timestamp":252.5,"duration":0.029998779296875,"other":"shape0","detail":"Cube.015"},{"actutorId":65,"timestamp":252.7899932861328,"duration":0.029998779296875,"other":"shape0","detail":"Cube.011"},{"actutorId":65,"timestamp":252.7899932861328,"duration":0.029998779296875,"other":"shape0","detail":"Cube.011"},{"actutorId":66,"timestamp":252.55999755859376,"duration":0.279998779296875,"other":"shape0","detail":"Cube.017"},{"actutorId":64,"timestamp":252.52999877929688,"duration":0.30999755859375,"other":"shape0","detail":"Cube.017"},{"actutorId":105,"timestamp":252.83999633789063,"duration":0.029998779296875,"other":"shape0","detail":"Cube.017"},{"actutorId":76,"timestamp":252.72999572753907,"duration":0.1399993896484375,"other":"shape0","detail":"Cube.017"},{"actutorId":76,"timestamp":252.72999572753907,"duration":0.1399993896484375,"other":"shape0","detail":"Cube.017"},{"actutorId":76,"timestamp":252.72999572753907,"duration":0.1399993896484375,"other":"shape0","detail":"Cube.017"},{"actutorId":77,"timestamp":252.8199920654297,"duration":0.0800018310546875,"other":"shape0","detail":"Cube.017"},{"actutorId":77,"timestamp":252.8199920654297,"duration":0.0800018310546875,"other":"shape0","detail":"Cube.017"},{"actutorId":78,"timestamp":252.5,"duration":0.42999267578125,"other":"shape0","detail":"Cube.017"},{"actutorId":160,"timestamp":252.11000061035157,"duration":0.92999267578125,"other":"shape0","detail":"Cube.006"},{"actutorId":136,"timestamp":253.00999450683595,"duration":0.029998779296875,"other":"shape0","detail":"Cube.006"},{"actutorId":151,"timestamp":251.97000122070313,"duration":1.0699920654296876,"other":"shape0","detail":"Cube.006"},{"actutorId":152,"timestamp":251.72000122070313,"duration":1.339996337890625,"other":"shape0","detail":"Cube.006"},{"actutorId":153,"timestamp":251.75,"duration":1.30999755859375,"other":"shape0","detail":"Cube.006"},{"actutorId":154,"timestamp":251.75,"duration":1.30999755859375,"other":"shape0","detail":"Cube.006"},{"actutorId":155,"timestamp":251.75,"duration":1.30999755859375,"other":"shape0","detail":"Cube.006"},{"actutorId":161,"timestamp":252.13999938964845,"duration":0.9199981689453125,"other":"shape0","detail":"Cube.006"},{"actutorId":156,"timestamp":251.75,"duration":1.30999755859375,"other":"shape0","detail":"Cube.006"},{"actutorId":157,"timestamp":251.72000122070313,"duration":1.339996337890625,"other":"shape0","detail":"Cube.006"},{"actutorId":158,"timestamp":251.72000122070313,"duration":1.339996337890625,"other":"shape0","detail":"Cube.006"},{"actutorId":159,"timestamp":251.9499969482422,"duration":1.1100006103515626,"other":"shape0","detail":"Cube.006"},{"actutorId":162,"timestamp":252.11000061035157,"duration":1.0,"other":"shape0","detail":"Cube.006"},{"actutorId":163,"timestamp":252.04998779296876,"duration":1.0600128173828126,"other":"shape0","detail":"Cube.006"},{"actutorId":164,"timestamp":251.9499969482422,"duration":1.1699981689453126,"other":"shape0","detail":"Cube.006"},{"actutorId":165,"timestamp":251.84999084472657,"duration":1.2700042724609376,"other":"shape0","detail":"Cube.006"},{"actutorId":166,"timestamp":252.0,"duration":1.1199951171875,"other":"shape0","detail":"Cube.006"},{"actutorId":167,"timestamp":251.8300018310547,"duration":1.29998779296875,"other":"shape0","detail":"Cube.006"},{"actutorId":169,"timestamp":251.8300018310547,"duration":1.29998779296875,"other":"shape0","detail":"Cube.006"},{"actutorId":170,"timestamp":252.0,"duration":1.1299896240234376,"other":"shape0","detail":"Cube.006"},{"actutorId":168,"timestamp":251.8300018310547,"duration":1.3199920654296876,"other":"shape0","detail":"Cube.006"},{"actutorId":65,"timestamp":257.5400085449219,"duration":0.04998779296875,"other":"shape1","detail":"Cube.011"},{"actutorId":108,"timestamp":257.5400085449219,"duration":0.04998779296875,"other":"shape1","detail":"Cube.017"},{"actutorId":95,"timestamp":257.55999755859377,"duration":0.029998779296875,"other":"shape1","detail":"Cube.017"},{"actutorId":108,"timestamp":257.6199951171875,"duration":0.029998779296875,"other":"shape1","detail":"Cube.017"},{"actutorId":65,"timestamp":257.67999267578127,"duration":0.05999755859375,"other":"shape1","detail":"Cube.011"},{"actutorId":108,"timestamp":257.67999267578127,"duration":0.05999755859375,"other":"shape1","detail":"Cube.017"},{"actutorId":95,"timestamp":257.67999267578127,"duration":0.05999755859375,"other":"shape1","detail":"Cube.017"},{"actutorId":75,"timestamp":257.47998046875,"duration":0.350006103515625,"other":"shape1","detail":"Cube.017"},{"actutorId":137,"timestamp":257.739990234375,"duration":0.089996337890625,"other":"shape1","detail":"Cube.006"},{"actutorId":108,"timestamp":257.8599853515625,"duration":0.050018310546875,"other":"shape1","detail":"Cube.017"},{"actutorId":96,"timestamp":257.5099792480469,"duration":0.71002197265625,"other":"shape1","detail":"Cube.017"},{"actutorId":97,"timestamp":257.5099792480469,"duration":0.57000732421875,"other":"shape1","detail":"Cube.017"},{"actutorId":107,"timestamp":257.5099792480469,"duration":1.33001708984375,"other":"shape1","detail":"Cube.017"},{"actutorId":106,"timestamp":258.04998779296877,"duration":0.1400146484375,"other":"shape1","detail":"Cube.011"},{"actutorId":94,"timestamp":257.5899963378906,"duration":1.139984130859375,"other":"shape1","detail":"Cube.017"},{"actutorId":75,"timestamp":257.9100036621094,"duration":0.8800048828125,"other":"shape1","detail":"Cube.017"},{"actutorId":105,"timestamp":257.55999755859377,"duration":1.30999755859375,"other":"shape1","detail":"Cube.017"},{"actutorId":96,"timestamp":257.5099792480469,"duration":0.71002197265625,"other":"shape1","detail":"Cube.017"},{"actutorId":137,"timestamp":257.94000244140627,"duration":0.199981689453125,"other":"shape1","detail":"Cube.006"},{"actutorId":106,"timestamp":258.04998779296877,"duration":0.1400146484375,"other":"shape1","detail":"Cube.011"},{"actutorId":93,"timestamp":257.6199951171875,"duration":0.57000732421875,"other":"shape1","detail":"Cube.017"},{"actutorId":74,"timestamp":257.4499816894531,"duration":0.77001953125,"other":"shape1","detail":"Cube.017"},{"actutorId":104,"timestamp":257.5400085449219,"duration":0.67999267578125,"other":"shape1","detail":"Cube.017"},{"actutorId":96,"timestamp":257.5099792480469,"duration":0.71002197265625,"other":"shape1","detail":"Cube.017"},{"actutorId":95,"timestamp":258.0199890136719,"duration":0.850006103515625,"other":"shape1","detail":"Cube.017"},{"actutorId":161,"timestamp":257.989990234375,"duration":0.300018310546875,"other":"shape1","detail":"Cube.006"},{"actutorId":136,"timestamp":257.7699890136719,"duration":0.52001953125,"other":"shape1","detail":"Cube.006"},{"actutorId":160,"timestamp":257.7099914550781,"duration":0.649993896484375,"other":"shape1","detail":"Cube.006"},{"actutorId":65,"timestamp":258.2900085449219,"duration":0.089996337890625,"other":"shape1","detail":"Cube.017"},{"actutorId":162,"timestamp":257.7699890136719,"duration":0.6400146484375,"other":"shape1","detail":"Cube.006"},{"actutorId":106,"timestamp":258.29998779296877,"duration":0.490020751953125,"other":"shape1","detail":"Cube.017"},{"actutorId":94,"timestamp":257.5899963378906,"duration":1.139984130859375,"other":"shape1","detail":"Cube.017"},{"actutorId":106,"timestamp":258.29998779296877,"duration":0.490020751953125,"other":"shape1","detail":"Cube.017"},{"actutorId":78,"timestamp":258.2900085449219,"duration":0.5,"other":"shape1","detail":"Cube.017"},{"actutorId":75,"timestamp":257.9100036621094,"duration":0.8800048828125,"other":"shape1","detail":"Cube.017"},{"actutorId":65,"timestamp":258.6199951171875,"duration":0.19000244140625,"other":"shape1","detail":"Cube.011"},{"actutorId":65,"timestamp":258.6199951171875,"duration":0.19000244140625,"other":"shape1","detail":"Cube.011"},{"actutorId":66,"timestamp":258.1600036621094,"duration":0.67999267578125,"other":"shape1","detail":"Cube.017"},{"actutorId":64,"timestamp":258.2200012207031,"duration":0.6199951171875,"other":"shape1","detail":"Cube.017"},{"actutorId":107,"timestamp":257.5099792480469,"duration":1.33001708984375,"other":"shape1","detail":"Cube.017"},{"actutorId":105,"timestamp":257.55999755859377,"duration":1.30999755859375,"other":"shape1","detail":"Cube.017"},{"actutorId":76,"timestamp":258.2200012207031,"duration":0.649993896484375,"other":"shape1","detail":"Cube.015"},{"actutorId":76,"timestamp":258.2200012207031,"duration":0.649993896484375,"other":"shape1","detail":"Cube.015"},{"actutorId":95,"timestamp":258.0199890136719,"duration":0.850006103515625,"other":"shape1","detail":"Cube.017"},{"actutorId":95,"timestamp":258.0199890136719,"duration":0.850006103515625,"other":"shape1","detail":"Cube.017"},{"actutorId":77,"timestamp":258.6999816894531,"duration":0.20001220703125,"other":"shape1","detail":"Cube.011"},{"actutorId":77,"timestamp":258.6999816894531,"duration":0.20001220703125,"other":"shape1","detail":"Cube.011"},{"actutorId":160,"timestamp":258.8699951171875,"duration":0.17999267578125,"other":"shape1","detail":"Cube.006"},{"actutorId":140,"timestamp":258.9100036621094,"duration":0.139984130859375,"other":"shape1","detail":"Cube.006"},{"actutorId":139,"timestamp":258.9599914550781,"duration":0.089996337890625,"other":"shape1","detail":"Cube.006"},{"actutorId":157,"timestamp":257.739990234375,"duration":1.33001708984375,"other":"shape1","detail":"Cube.006"},{"actutorId":158,"timestamp":257.739990234375,"duration":1.33001708984375,"other":"shape1","detail":"Cube.006"},{"actutorId":159,"timestamp":257.739990234375,"duration":1.33001708984375,"other":"shape1","detail":"Cube.006"},{"actutorId":138,"timestamp":258.9599914550781,"duration":0.110015869140625,"other":"shape1","detail":"Cube.006"},{"actutorId":137,"timestamp":258.8699951171875,"duration":0.20001220703125,"other":"shape1","detail":"Cube.006"},{"actutorId":151,"timestamp":258.1600036621094,"duration":0.910003662109375,"other":"shape1","detail":"Cube.006"},{"actutorId":152,"timestamp":257.739990234375,"duration":1.33001708984375,"other":"shape1","detail":"Cube.006"},{"actutorId":161,"timestamp":258.9599914550781,"duration":0.1300048828125,"other":"shape1","detail":"Cube.006"},{"actutorId":156,"timestamp":257.739990234375,"duration":1.350006103515625,"other":"shape1","detail":"Cube.006"},{"actutorId":136,"timestamp":258.8999938964844,"duration":0.19000244140625,"other":"shape1","detail":"Cube.006"},{"actutorId":153,"timestamp":257.739990234375,"duration":1.350006103515625,"other":"shape1","detail":"Cube.006"},{"actutorId":154,"timestamp":257.7699890136719,"duration":1.32000732421875,"other":"shape1","detail":"Cube.006"},{"actutorId":155,"timestamp":257.7699890136719,"duration":1.32000732421875,"other":"shape1","detail":"Cube.006"},{"actutorId":162,"timestamp":258.7900085449219,"duration":0.319976806640625,"other":"shape1","detail":"Cube.006"},{"actutorId":163,"timestamp":257.79998779296877,"duration":1.33001708984375,"other":"shape1","detail":"Cube.006"},{"actutorId":164,"timestamp":257.79998779296877,"duration":1.339996337890625,"other":"shape1","detail":"Cube.006"},{"actutorId":165,"timestamp":257.8299865722656,"duration":1.32000732421875,"other":"shape1","detail":"Cube.006"},{"actutorId":169,"timestamp":257.8299865722656,"duration":1.33001708984375,"other":"shape1","detail":"Cube.006"},{"actutorId":167,"timestamp":257.8299865722656,"duration":1.33001708984375,"other":"shape1","detail":"Cube.006"},{"actutorId":170,"timestamp":257.8299865722656,"duration":1.33001708984375,"other":"shape1","detail":"Cube.006"},{"actutorId":166,"timestamp":257.8299865722656,"duration":1.33001708984375,"other":"shape1","detail":"Cube.006"},{"actutorId":168,"timestamp":257.8599853515625,"duration":1.32000732421875,"other":"shape1","detail":"Cube.006"},{"actutorId":93,"timestamp":262.5400085449219,"duration":0.199981689453125,"other":"shape2","detail":"Cube.031"},{"actutorId":63,"timestamp":262.7200012207031,"duration":0.1099853515625,"other":"shape2","detail":"Cube.031"},{"actutorId":79,"timestamp":262.6099853515625,"duration":0.220001220703125,"other":"shape2","detail":"Cube.034"},{"actutorId":79,"timestamp":262.6099853515625,"duration":0.220001220703125,"other":"shape2","detail":"Cube.034"},{"actutorId":106,"timestamp":262.7699890136719,"duration":0.160003662109375,"other":"shape2","detail":"Cube.031"},{"actutorId":170,"timestamp":262.66998291015627,"duration":0.3800048828125,"other":"shape2","detail":"Cube.011"},{"actutorId":101,"timestamp":262.6499938964844,"duration":0.459991455078125,"other":"shape2","detail":"Cube.008"},{"actutorId":73,"timestamp":262.6199951171875,"duration":0.54998779296875,"other":"shape2","detail":"Cube.022"},{"actutorId":161,"timestamp":262.5400085449219,"duration":0.629974365234375,"other":"shape2","detail":"Cube.007"},{"actutorId":163,"timestamp":262.5799865722656,"duration":0.670013427734375,"other":"shape2","detail":"Cube.007"},{"actutorId":162,"timestamp":262.55999755859377,"duration":0.6300048828125,"other":"shape2","detail":"Cube.007"},{"actutorId":160,"timestamp":262.5,"duration":0.69000244140625,"other":"shape2","detail":"Cube.007"},{"actutorId":169,"timestamp":262.6499938964844,"duration":0.540008544921875,"other":"shape2","detail":"Cube.011"},{"actutorId":159,"timestamp":262.5199890136719,"duration":0.70001220703125,"other":"shape2","detail":"Cube.007"},{"actutorId":166,"timestamp":262.6099853515625,"duration":0.610015869140625,"other":"shape2","detail":"Cube.011"},{"actutorId":163,"timestamp":262.5799865722656,"duration":0.670013427734375,"other":"shape2","detail":"Cube.007"},{"actutorId":164,"timestamp":262.6099853515625,"duration":0.70001220703125,"other":"shape2","detail":"Cube.007"},{"actutorId":165,"timestamp":262.6099853515625,"duration":0.70001220703125,"other":"shape2","detail":"Cube.007"},{"actutorId":158,"timestamp":262.5199890136719,"duration":0.790008544921875,"other":"shape2","detail":"Cube.007"},{"actutorId":167,"timestamp":262.6499938964844,"duration":0.600006103515625,"other":"shape2","detail":"Cube.011"},{"actutorId":168,"timestamp":262.6499938964844,"duration":0.600006103515625,"other":"shape2","detail":"Cube.011"},{"actutorId":164,"timestamp":262.6099853515625,"duration":0.70001220703125,"other":"shape2","detail":"Cube.007"},{"actutorId":165,"timestamp":262.6099853515625,"duration":0.70001220703125,"other":"shape2","detail":"Cube.007"},{"actutorId":158,"timestamp":262.5199890136719,"duration":0.790008544921875,"other":"shape2","detail":"Cube.007"},{"actutorId":93,"timestamp":263.1099853515625,"duration":0.20001220703125,"other":"shape2","detail":"Cube.031"},{"actutorId":79,"timestamp":263.0799865722656,"duration":0.839996337890625,"other":"shape2","detail":"Cube.036"},{"actutorId":79,"timestamp":263.0799865722656,"duration":0.839996337890625,"other":"shape2","detail":"Cube.036"},{"actutorId":78,"timestamp":262.6099853515625,"duration":1.30999755859375,"other":"shape2","detail":"Cube.034"},{"actutorId":70,"timestamp":263.55999755859377,"duration":0.290008544921875,"other":"shape2","detail":"Cube.020"},{"actutorId":105,"timestamp":263.4700012207031,"duration":0.339996337890625,"other":"shape2","detail":"Cube.020"},{"actutorId":105,"timestamp":263.4700012207031,"duration":0.339996337890625,"other":"shape2","detail":"Cube.020"},{"actutorId":104,"timestamp":262.489990234375,"duration":1.32000732421875,"other":"shape2","detail":"Cube.020"},{"actutorId":109,"timestamp":262.5,"duration":1.30999755859375,"other":"shape2","detail":"Cube.036"},{"actutorId":109,"timestamp":262.5,"duration":1.30999755859375,"other":"shape2","detail":"Cube.036"},{"actutorId":109,"timestamp":262.5,"duration":1.30999755859375,"other":"shape2","detail":"Cube.036"},{"actutorId":108,"timestamp":262.5400085449219,"duration":1.269989013671875,"other":"shape2","detail":"Cube.034"},{"actutorId":108,"timestamp":262.5400085449219,"duration":1.269989013671875,"other":"shape2","detail":"Cube.034"},{"actutorId":108,"timestamp":262.5400085449219,"duration":1.269989013671875,"other":"shape2","detail":"Cube.034"},{"actutorId":108,"timestamp":262.5400085449219,"duration":1.269989013671875,"other":"shape2","detail":"Cube.034"},{"actutorId":107,"timestamp":262.5,"duration":1.30999755859375,"other":"shape2","detail":"Cube.020"},{"actutorId":107,"timestamp":262.5,"duration":1.30999755859375,"other":"shape2","detail":"Cube.020"},{"actutorId":106,"timestamp":263.3299865722656,"duration":0.480010986328125,"other":"shape2","detail":"Cube.031"},{"actutorId":106,"timestamp":263.3299865722656,"duration":0.480010986328125,"other":"shape2","detail":"Cube.031"},{"actutorId":103,"timestamp":262.5,"duration":1.30999755859375,"other":"shape2","detail":"Cube.022"},{"actutorId":103,"timestamp":262.5,"duration":1.30999755859375,"other":"shape2","detail":"Cube.022"},{"actutorId":102,"timestamp":263.3899841308594,"duration":0.420013427734375,"other":"shape2","detail":"Cube.022"},{"actutorId":102,"timestamp":263.3899841308594,"duration":0.420013427734375,"other":"shape2","detail":"Cube.022"},{"actutorId":101,"timestamp":263.30999755859377,"duration":0.5,"other":"shape2","detail":"Cube.008"},{"actutorId":101,"timestamp":263.30999755859377,"duration":0.5,"other":"shape2","detail":"Cube.008"},{"actutorId":66,"timestamp":262.5400085449219,"duration":1.30999755859375,"other":"shape2","detail":"Cube.020"},{"actutorId":67,"timestamp":262.5199890136719,"duration":1.33001708984375,"other":"shape2","detail":"Cube.020"},{"actutorId":68,"timestamp":263.4700012207031,"duration":0.3800048828125,"other":"shape2","detail":"Cube.022"},{"actutorId":68,"timestamp":263.4700012207031,"duration":0.3800048828125,"other":"shape2","detail":"Cube.022"},{"actutorId":69,"timestamp":262.5199890136719,"duration":1.33001708984375,"other":"shape2","detail":"Cube.020"},{"actutorId":70,"timestamp":263.55999755859377,"duration":0.290008544921875,"other":"shape2","detail":"Cube.020"},{"actutorId":71,"timestamp":263.3899841308594,"duration":0.46002197265625,"other":"shape2","detail":"Cube.008"},{"actutorId":71,"timestamp":263.3899841308594,"duration":0.46002197265625,"other":"shape2","detail":"Cube.008"},{"actutorId":94,"timestamp":262.5400085449219,"duration":1.30999755859375,"other":"shape2","detail":"Cube.020"},{"actutorId":94,"timestamp":262.5400085449219,"duration":1.30999755859375,"other":"shape2","detail":"Cube.020"},{"actutorId":95,"timestamp":262.5400085449219,"duration":1.30999755859375,"other":"shape2","detail":"Cube.031"},{"actutorId":95,"timestamp":262.5400085449219,"duration":1.30999755859375,"other":"shape2","detail":"Cube.031"},{"actutorId":157,"timestamp":262.5199890136719,"duration":1.33001708984375,"other":"shape2","detail":"Cube.011"},{"actutorId":157,"timestamp":262.5199890136719,"duration":1.33001708984375,"other":"shape2","detail":"Cube.011"},{"actutorId":158,"timestamp":263.5099792480469,"duration":0.34002685546875,"other":"shape2","detail":"Cube.011"},{"actutorId":158,"timestamp":263.5099792480469,"duration":0.34002685546875,"other":"shape2","detail":"Cube.011"},{"actutorId":159,"timestamp":263.55999755859377,"duration":0.290008544921875,"other":"shape2","detail":"Cube.007"},{"actutorId":151,"timestamp":262.55999755859377,"duration":1.290008544921875,"other":"shape2","detail":"Cube.010"},{"actutorId":151,"timestamp":262.55999755859377,"duration":1.290008544921875,"other":"shape2","detail":"Cube.010"},{"actutorId":152,"timestamp":262.55999755859377,"duration":1.290008544921875,"other":"shape2","detail":"Cube.011"},{"actutorId":65,"timestamp":262.55999755859377,"duration":1.290008544921875,"other":"shape2","detail":"Cube.020"},{"actutorId":97,"timestamp":262.55999755859377,"duration":1.290008544921875,"other":"shape2","detail":"Cube.022"},{"actutorId":97,"timestamp":262.55999755859377,"duration":1.290008544921875,"other":"shape2","detail":"Cube.022"},{"actutorId":98,"timestamp":262.55999755859377,"duration":1.290008544921875,"other":"shape2","detail":"Cube.022"},{"actutorId":98,"timestamp":262.55999755859377,"duration":1.290008544921875,"other":"shape2","detail":"Cube.022"},{"actutorId":99,"timestamp":262.6199951171875,"duration":1.230010986328125,"other":"shape2","detail":"Cube.022"},{"actutorId":99,"timestamp":262.6199951171875,"duration":1.230010986328125,"other":"shape2","detail":"Cube.022"},{"actutorId":100,"timestamp":262.5400085449219,"duration":1.30999755859375,"other":"shape2","detail":"Cube.008"},{"actutorId":100,"timestamp":262.5400085449219,"duration":1.30999755859375,"other":"shape2","detail":"Cube.008"},{"actutorId":62,"timestamp":263.44000244140627,"duration":0.410003662109375,"other":"shape2","detail":"Cube.034"},{"actutorId":62,"timestamp":263.44000244140627,"duration":0.410003662109375,"other":"shape2","detail":"Cube.034"},{"actutorId":62,"timestamp":263.44000244140627,"duration":0.410003662109375,"other":"shape2","detail":"Cube.034"},{"actutorId":63,"timestamp":263.3599853515625,"duration":0.490020751953125,"other":"shape2","detail":"Cube.034"},{"actutorId":63,"timestamp":263.3599853515625,"duration":0.490020751953125,"other":"shape2","detail":"Cube.034"},{"actutorId":63,"timestamp":263.3599853515625,"duration":0.490020751953125,"other":"shape2","detail":"Cube.034"},{"actutorId":64,"timestamp":262.55999755859377,"duration":1.290008544921875,"other":"shape2","detail":"Cube.020"},{"actutorId":64,"timestamp":262.55999755859377,"duration":1.290008544921875,"other":"shape2","detail":"Cube.020"},{"actutorId":75,"timestamp":262.5799865722656,"duration":1.300018310546875,"other":"shape2","detail":"Cube.020"},{"actutorId":74,"timestamp":262.5799865722656,"duration":1.300018310546875,"other":"shape2","detail":"Cube.020"},{"actutorId":73,"timestamp":263.2799987792969,"duration":0.600006103515625,"other":"shape2","detail":"Cube.022"},{"actutorId":73,"timestamp":263.2799987792969,"duration":0.600006103515625,"other":"shape2","detail":"Cube.022"},{"actutorId":72,"timestamp":262.55999755859377,"duration":1.32000732421875,"other":"shape2","detail":"Cube.020"},{"actutorId":96,"timestamp":262.55999755859377,"duration":1.32000732421875,"other":"shape2","detail":"Cube.020"},{"actutorId":96,"timestamp":262.55999755859377,"duration":1.32000732421875,"other":"shape2","detail":"Cube.020"},{"actutorId":76,"timestamp":262.6199951171875,"duration":1.260009765625,"other":"shape2","detail":"Cube.020"},{"actutorId":162,"timestamp":263.6399841308594,"duration":0.240020751953125,"other":"shape2","detail":"Cube.007"},{"actutorId":156,"timestamp":262.5400085449219,"duration":1.339996337890625,"other":"shape2","detail":"Cube.011"},{"actutorId":156,"timestamp":262.5400085449219,"duration":1.339996337890625,"other":"shape2","detail":"Cube.011"},{"actutorId":153,"timestamp":262.55999755859377,"duration":1.32000732421875,"other":"shape2","detail":"Cube.011"},{"actutorId":154,"timestamp":262.55999755859377,"duration":1.32000732421875,"other":"shape2","detail":"Cube.011"},{"actutorId":155,"timestamp":262.55999755859377,"duration":1.32000732421875,"other":"shape2","detail":"Cube.011"},{"actutorId":76,"timestamp":262.6199951171875,"duration":1.260009765625,"other":"shape2","detail":"Cube.020"},{"actutorId":79,"timestamp":263.0799865722656,"duration":0.839996337890625,"other":"shape2","detail":"Cube.036"},{"actutorId":78,"timestamp":262.6099853515625,"duration":1.30999755859375,"other":"shape2","detail":"Cube.034"},{"actutorId":78,"timestamp":262.6099853515625,"duration":1.30999755859375,"other":"shape2","detail":"Cube.034"},{"actutorId":78,"timestamp":262.6099853515625,"duration":1.30999755859375,"other":"shape2","detail":"Cube.034"},{"actutorId":77,"timestamp":262.6099853515625,"duration":1.30999755859375,"other":"shape2","detail":"Cube.031"},{"actutorId":77,"timestamp":262.6099853515625,"duration":1.30999755859375,"other":"shape2","detail":"Cube.031"},{"actutorId":163,"timestamp":263.8800048828125,"duration":0.03997802734375,"other":"shape2","detail":"Cube.007"},{"actutorId":163,"timestamp":263.8800048828125,"duration":0.03997802734375,"other":"shape2","detail":"Cube.007"},{"actutorId":164,"timestamp":263.5099792480469,"duration":0.410003662109375,"other":"shape2","detail":"Cube.011"},{"actutorId":164,"timestamp":263.5099792480469,"duration":0.410003662109375,"other":"shape2","detail":"Cube.011"},{"actutorId":165,"timestamp":263.5099792480469,"duration":0.420013427734375,"other":"shape2","detail":"Cube.011"},{"actutorId":169,"timestamp":263.91998291015627,"duration":0.010009765625,"other":"shape2","detail":"Cube.011"},{"actutorId":165,"timestamp":263.5099792480469,"duration":0.420013427734375,"other":"shape2","detail":"Cube.011"},{"actutorId":166,"timestamp":263.6399841308594,"duration":0.290008544921875,"other":"shape2","detail":"Cube.011"},{"actutorId":167,"timestamp":263.5299987792969,"duration":0.42999267578125,"other":"shape2","detail":"Cube.011"},{"actutorId":168,"timestamp":263.5299987792969,"duration":0.42999267578125,"other":"shape2","detail":"Cube.011"},{"actutorId":108,"timestamp":268.6600036621094,"duration":0.97998046875,"other":"shape3","detail":"Cube.035"},{"actutorId":80,"timestamp":268.82000732421877,"duration":0.1199951171875,"other":"shape3","detail":"Cube.036"},{"actutorId":100,"timestamp":268.7900085449219,"duration":0.17999267578125,"other":"shape3","detail":"Cube.020"},{"actutorId":78,"timestamp":268.6300048828125,"duration":1.069976806640625,"other":"shape3","detail":"Cube.035"},{"actutorId":102,"timestamp":268.739990234375,"duration":0.339996337890625,"other":"shape3","detail":"Cube.020"},{"actutorId":109,"timestamp":268.489990234375,"duration":1.07000732421875,"other":"shape3","detail":"Cube.036"},{"actutorId":109,"timestamp":268.489990234375,"duration":1.07000732421875,"other":"shape3","detail":"Cube.036"},{"actutorId":108,"timestamp":268.6600036621094,"duration":0.97998046875,"other":"shape3","detail":"Cube.035"},{"actutorId":167,"timestamp":269.1600036621094,"duration":0.259979248046875,"other":"shape3","detail":"Cube.011"},{"actutorId":168,"timestamp":269.0799865722656,"duration":0.339996337890625,"other":"shape3","detail":"Cube.011"},{"actutorId":103,"timestamp":268.5199890136719,"duration":0.920013427734375,"other":"shape3","detail":"Cube.020"},{"actutorId":79,"timestamp":268.6099853515625,"duration":1.029998779296875,"other":"shape3","detail":"Cube.036"},{"actutorId":79,"timestamp":268.6099853515625,"duration":1.029998779296875,"other":"shape3","detail":"Cube.036"},{"actutorId":164,"timestamp":269.25,"duration":0.19000244140625,"other":"shape3","detail":"Cube.007"},{"actutorId":165,"timestamp":269.04998779296877,"duration":0.3900146484375,"other":"shape3","detail":"Cube.007"},{"actutorId":158,"timestamp":269.3299865722656,"duration":0.17999267578125,"other":"shape3","detail":"Cube.007"},{"actutorId":78,"timestamp":268.6300048828125,"duration":1.069976806640625,"other":"shape3","detail":"Cube.035"},{"actutorId":99,"timestamp":268.5199890136719,"duration":0.95001220703125,"other":"shape3","detail":"Cube.020"},{"actutorId":158,"timestamp":269.3299865722656,"duration":0.17999267578125,"other":"shape3","detail":"Cube.007"},{"actutorId":106,"timestamp":268.489990234375,"duration":1.019989013671875,"other":"shape3","detail":"Cube.020"},{"actutorId":104,"timestamp":268.489990234375,"duration":1.040008544921875,"other":"shape3","detail":"Cube.020"},{"actutorId":157,"timestamp":268.5199890136719,"duration":1.040008544921875,"other":"shape3","detail":"Cube.007"},{"actutorId":76,"timestamp":268.5799865722656,"duration":0.95001220703125,"other":"shape3","detail":"Cube.020"},{"actutorId":155,"timestamp":268.54998779296877,"duration":1.010009765625,"other":"shape3","detail":"Cube.011"},{"actutorId":98,"timestamp":268.54998779296877,"duration":1.010009765625,"other":"shape3","detail":"Cube.020"},{"actutorId":109,"timestamp":268.489990234375,"duration":1.07000732421875,"other":"shape3","detail":"Cube.036"},{"actutorId":107,"timestamp":268.489990234375,"duration":1.100006103515625,"other":"shape3","detail":"Cube.020"},{"actutorId":156,"timestamp":268.5199890136719,"duration":1.07000732421875,"other":"shape3","detail":"Cube.007"},{"actutorId":157,"timestamp":268.5199890136719,"duration":1.040008544921875,"other":"shape3","detail":"Cube.007"},{"actutorId":105,"timestamp":268.489990234375,"duration":1.100006103515625,"other":"shape3","detail":"Cube.020"},{"actutorId":77,"timestamp":268.6099853515625,"duration":0.980010986328125,"other":"shape3","detail":"Cube.020"},{"actutorId":77,"timestamp":268.6099853515625,"duration":0.980010986328125,"other":"shape3","detail":"Cube.020"},{"actutorId":95,"timestamp":268.5199890136719,"duration":1.290008544921875,"other":"shape3","detail":"Cube.020"},{"actutorId":156,"timestamp":268.5199890136719,"duration":1.07000732421875,"other":"shape3","detail":"Cube.007"},{"actutorId":107,"timestamp":268.489990234375,"duration":1.100006103515625,"other":"shape3","detail":"Cube.020"},{"actutorId":97,"timestamp":268.54998779296877,"duration":1.089996337890625,"other":"shape3","detail":"Cube.020"},{"actutorId":108,"timestamp":268.6600036621094,"duration":0.97998046875,"other":"shape3","detail":"Cube.035"},{"actutorId":108,"timestamp":268.6600036621094,"duration":0.97998046875,"other":"shape3","detail":"Cube.035"},{"actutorId":79,"timestamp":268.6099853515625,"duration":1.029998779296875,"other":"shape3","detail":"Cube.036"},{"actutorId":92,"timestamp":269.6399841308594,"duration":0.180023193359375,"other":"shape3","detail":"Cube.036"},{"actutorId":78,"timestamp":268.6300048828125,"duration":1.069976806640625,"other":"shape3","detail":"Cube.035"},{"actutorId":78,"timestamp":268.6300048828125,"duration":1.069976806640625,"other":"shape3","detail":"Cube.035"},{"actutorId":96,"timestamp":268.54998779296877,"duration":1.209991455078125,"other":"shape3","detail":"Cube.020"},{"actutorId":94,"timestamp":269.66998291015627,"duration":0.1500244140625,"other":"shape3","detail":"Cube.020"},{"actutorId":94,"timestamp":269.66998291015627,"duration":0.1500244140625,"other":"shape3","detail":"Cube.020"},{"actutorId":95,"timestamp":268.5199890136719,"duration":1.290008544921875,"other":"shape3","detail":"Cube.020"},{"actutorId":93,"timestamp":269.5899963378906,"duration":0.230010986328125,"other":"shape3","detail":"Cube.031"},{"actutorId":93,"timestamp":269.5899963378906,"duration":0.230010986328125,"other":"shape3","detail":"Cube.031"},{"actutorId":93,"timestamp":269.5899963378906,"duration":0.230010986328125,"other":"shape3","detail":"Cube.031"},{"actutorId":93,"timestamp":269.5899963378906,"duration":0.230010986328125,"other":"shape3","detail":"Cube.031"},{"actutorId":94,"timestamp":269.66998291015627,"duration":0.1500244140625,"other":"shape3","detail":"Cube.020"},{"actutorId":94,"timestamp":269.66998291015627,"duration":0.1500244140625,"other":"shape3","detail":"Cube.020"},{"actutorId":92,"timestamp":269.6399841308594,"duration":0.180023193359375,"other":"shape3","detail":"Cube.036"},{"actutorId":154,"timestamp":268.54998779296877,"duration":1.279998779296875,"other":"shape3","detail":"Cube.011"},{"actutorId":153,"timestamp":268.54998779296877,"duration":1.279998779296875,"other":"shape3","detail":"Cube.011"},{"actutorId":152,"timestamp":268.54998779296877,"duration":1.279998779296875,"other":"shape3","detail":"Cube.011"},{"actutorId":151,"timestamp":268.54998779296877,"duration":1.279998779296875,"other":"shape3","detail":"Cube.011"},{"actutorId":151,"timestamp":268.54998779296877,"duration":1.279998779296875,"other":"shape3","detail":"Cube.011"},{"actutorId":164,"timestamp":274.4100036621094,"duration":0.389984130859375,"other":"shape4","detail":"Cube.017"},{"actutorId":154,"timestamp":274.3500061035156,"duration":0.529998779296875,"other":"shape4","detail":"Cube.017"},{"actutorId":136,"timestamp":274.2699890136719,"duration":0.959991455078125,"other":"shape4","detail":"Cube.017"},{"actutorId":156,"timestamp":274.32000732421877,"duration":0.66998291015625,"other":"shape4","detail":"Cube.017"},{"actutorId":165,"timestamp":274.2699890136719,"duration":0.779998779296875,"other":"shape4","detail":"Cube.017"},{"actutorId":155,"timestamp":274.32000732421877,"duration":0.759979248046875,"other":"shape4","detail":"Cube.017"},{"actutorId":167,"timestamp":274.989990234375,"duration":0.709991455078125,"other":"shape4","detail":"Cube.017"},{"actutorId":137,"timestamp":274.2900085449219,"duration":0.8699951171875,"other":"shape4","detail":"Cube.017"},{"actutorId":166,"timestamp":274.9100036621094,"duration":0.72998046875,"other":"shape4","detail":"Cube.015"},{"actutorId":136,"timestamp":274.2699890136719,"duration":0.959991455078125,"other":"shape4","detail":"Cube.017"},{"actutorId":125,"timestamp":275.04998779296877,"duration":0.20001220703125,"other":"shape4","detail":"Cube.011"},{"actutorId":126,"timestamp":274.6300048828125,"duration":0.80999755859375,"other":"shape4","detail":"Cube.017"},{"actutorId":135,"timestamp":274.5400085449219,"duration":0.899993896484375,"other":"shape4","detail":"Cube.017"},{"actutorId":125,"timestamp":275.4700012207031,"duration":0.139984130859375,"other":"shape4","detail":"Cube.017"},{"actutorId":125,"timestamp":275.4700012207031,"duration":0.139984130859375,"other":"shape4","detail":"Cube.017"},{"actutorId":124,"timestamp":274.9700012207031,"duration":0.66998291015625,"other":"shape4","detail":"Cube.017"},{"actutorId":166,"timestamp":274.9100036621094,"duration":0.72998046875,"other":"shape4","detail":"Cube.015"},{"actutorId":166,"timestamp":274.9100036621094,"duration":0.72998046875,"other":"shape4","detail":"Cube.015"},{"actutorId":167,"timestamp":274.989990234375,"duration":0.709991455078125,"other":"shape4","detail":"Cube.017"},{"actutorId":168,"timestamp":275.25,"duration":0.449981689453125,"other":"shape4","detail":"Cube.017"},{"actutorId":105,"timestamp":275.3699951171875,"duration":0.420013427734375,"other":"shape4","detail":"Cube.006"},{"actutorId":104,"timestamp":275.3299865722656,"duration":0.46002197265625,"other":"shape4","detail":"Cube.006"},{"actutorId":103,"timestamp":275.1600036621094,"duration":0.639984130859375,"other":"shape4","detail":"Cube.006"},{"actutorId":102,"timestamp":275.04998779296877,"duration":0.75,"other":"shape4","detail":"Cube.006"},{"actutorId":101,"timestamp":274.989990234375,"duration":0.83001708984375,"other":"shape4","detail":"Cube.006"},{"actutorId":99,"timestamp":274.5099792480469,"duration":1.32000732421875,"other":"shape4","detail":"Cube.006"},{"actutorId":100,"timestamp":274.5099792480469,"duration":1.32000732421875,"other":"shape4","detail":"Cube.006"},{"actutorId":91,"timestamp":275.29998779296877,"duration":0.529998779296875,"other":"shape4","detail":"Cube.006"},{"actutorId":92,"timestamp":274.5099792480469,"duration":1.32000732421875,"other":"shape4","detail":"Cube.006"},{"actutorId":93,"timestamp":274.5099792480469,"duration":1.32000732421875,"other":"shape4","detail":"Cube.006"},{"actutorId":94,"timestamp":274.489990234375,"duration":1.339996337890625,"other":"shape4","detail":"Cube.006"},{"actutorId":95,"timestamp":274.489990234375,"duration":1.339996337890625,"other":"shape4","detail":"Cube.006"},{"actutorId":71,"timestamp":275.04998779296877,"duration":0.800018310546875,"other":"shape4","detail":"Cube.006"},{"actutorId":96,"timestamp":274.5099792480469,"duration":1.34002685546875,"other":"shape4","detail":"Cube.006"},{"actutorId":97,"timestamp":274.5099792480469,"duration":1.34002685546875,"other":"shape4","detail":"Cube.006"},{"actutorId":98,"timestamp":274.5099792480469,"duration":1.34002685546875,"other":"shape4","detail":"Cube.006"},{"actutorId":76,"timestamp":275.22998046875,"duration":0.6500244140625,"other":"shape4","detail":"Cube.006"},{"actutorId":75,"timestamp":275.55999755859377,"duration":0.32000732421875,"other":"shape4","detail":"Cube.006"},{"actutorId":73,"timestamp":275.41998291015627,"duration":0.46002197265625,"other":"shape4","detail":"Cube.006"},{"actutorId":72,"timestamp":275.3299865722656,"duration":0.550018310546875,"other":"shape4","detail":"Cube.006"},{"actutorId":77,"timestamp":275.1300048828125,"duration":0.769989013671875,"other":"shape4","detail":"Cube.006"},{"actutorId":74,"timestamp":275.5,"duration":0.399993896484375,"other":"shape4","detail":"Cube.006"},{"actutorId":80,"timestamp":275.3699951171875,"duration":0.54998779296875,"other":"shape4","detail":"Cube.006"},{"actutorId":79,"timestamp":275.29998779296877,"duration":0.6199951171875,"other":"shape4","detail":"Cube.006"},{"actutorId":78,"timestamp":275.22998046875,"duration":0.69000244140625,"other":"shape4","detail":"Cube.006"},{"actutorId":125,"timestamp":280.2599792480469,"duration":1.33001708984375,"other":"shape5","detail":"Cube.017"},{"actutorId":136,"timestamp":280.239990234375,"duration":0.610015869140625,"other":"shape5","detail":"Cube.017"},{"actutorId":124,"timestamp":280.2900085449219,"duration":0.589996337890625,"other":"shape5","detail":"Cube.017"},{"actutorId":126,"timestamp":280.239990234375,"duration":0.720001220703125,"other":"shape5","detail":"Cube.017"},{"actutorId":98,"timestamp":281.0199890136719,"duration":0.08001708984375,"other":"shape5","detail":"Cube.006"},{"actutorId":125,"timestamp":280.2599792480469,"duration":1.33001708984375,"other":"shape5","detail":"Cube.017"},{"actutorId":166,"timestamp":280.32000732421877,"duration":1.319976806640625,"other":"shape5","detail":"Cube.017"},{"actutorId":167,"timestamp":280.3699951171875,"duration":1.30999755859375,"other":"shape5","detail":"Cube.017"},{"actutorId":92,"timestamp":280.57000732421877,"duration":1.30999755859375,"other":"shape5","detail":"Cube.006"},{"actutorId":93,"timestamp":280.57000732421877,"duration":1.30999755859375,"other":"shape5","detail":"Cube.006"},{"actutorId":94,"timestamp":280.6000061035156,"duration":1.28997802734375,"other":"shape5","detail":"Cube.006"},{"actutorId":95,"timestamp":280.7900085449219,"duration":1.0999755859375,"other":"shape5","detail":"Cube.006"},{"actutorId":96,"timestamp":280.739990234375,"duration":1.19000244140625,"other":"shape5","detail":"Cube.006"},{"actutorId":97,"timestamp":280.7900085449219,"duration":1.139984130859375,"other":"shape5","detail":"Cube.006"},{"actutorId":98,"timestamp":281.5199890136719,"duration":0.410003662109375,"other":"shape5","detail":"Cube.006"},{"actutorId":99,"timestamp":281.6600036621094,"duration":0.279998779296875,"other":"shape5","detail":"Cube.006"},{"actutorId":100,"timestamp":281.8299865722656,"duration":0.110015869140625,"other":"shape5","detail":"Cube.006"},{"actutorId":72,"timestamp":287.7900085449219,"duration":0.129974365234375,"other":"shape6","detail":"Cube.010"},{"actutorId":110,"timestamp":287.82000732421877,"duration":0.16998291015625,"other":"shape6","detail":"Cube.049"},{"actutorId":109,"timestamp":287.8500061035156,"duration":0.269989013671875,"other":"shape6","detail":"Cube.011"},{"actutorId":99,"timestamp":287.8500061035156,"duration":0.29998779296875,"other":"shape6","detail":"Cube.010"},{"actutorId":155,"timestamp":287.8500061035156,"duration":0.649993896484375,"other":"shape6","detail":"Cube.020"},{"actutorId":99,"timestamp":288.239990234375,"duration":0.019989013671875,"other":"shape6","detail":"Cube.010"},{"actutorId":157,"timestamp":287.82000732421877,"duration":0.470001220703125,"other":"shape6","detail":"Cube.020"},{"actutorId":153,"timestamp":287.8500061035156,"duration":1.30999755859375,"other":"shape6","detail":"Cube.034"},{"actutorId":71,"timestamp":287.7900085449219,"duration":0.589996337890625,"other":"shape6","detail":"Cube.010"},{"actutorId":100,"timestamp":287.82000732421877,"duration":0.55999755859375,"other":"shape6","detail":"Cube.010"},{"actutorId":156,"timestamp":287.82000732421877,"duration":0.579986572265625,"other":"shape6","detail":"Cube.020"},{"actutorId":154,"timestamp":287.8500061035156,"duration":1.30999755859375,"other":"shape6","detail":"Cube.020"},{"actutorId":154,"timestamp":287.8500061035156,"duration":1.30999755859375,"other":"shape6","detail":"Cube.020"},{"actutorId":155,"timestamp":287.8500061035156,"duration":0.649993896484375,"other":"shape6","detail":"Cube.020"},{"actutorId":153,"timestamp":287.8500061035156,"duration":1.30999755859375,"other":"shape6","detail":"Cube.034"},{"actutorId":153,"timestamp":287.8500061035156,"duration":1.30999755859375,"other":"shape6","detail":"Cube.034"},{"actutorId":152,"timestamp":288.2099914550781,"duration":0.95001220703125,"other":"shape6","detail":"Cube.036"},{"actutorId":154,"timestamp":287.8500061035156,"duration":1.30999755859375,"other":"shape6","detail":"Cube.020"},{"actutorId":153,"timestamp":287.8500061035156,"duration":1.30999755859375,"other":"shape6","detail":"Cube.034"},{"actutorId":154,"timestamp":287.8500061035156,"duration":1.30999755859375,"other":"shape6","detail":"Cube.020"},{"actutorId":110,"timestamp":288.3299865722656,"duration":0.83001708984375,"other":"shape6","detail":"Cube.051"},{"actutorId":110,"timestamp":288.3299865722656,"duration":0.83001708984375,"other":"shape6","detail":"Cube.051"},{"actutorId":109,"timestamp":288.3800048828125,"duration":0.779998779296875,"other":"shape6","detail":"Cube.049"},{"actutorId":109,"timestamp":288.3800048828125,"duration":0.779998779296875,"other":"shape6","detail":"Cube.049"},{"actutorId":108,"timestamp":288.6000061035156,"duration":0.55999755859375,"other":"shape6","detail":"Cube.049"},{"actutorId":108,"timestamp":288.6000061035156,"duration":0.55999755859375,"other":"shape6","detail":"Cube.049"},{"actutorId":92,"timestamp":289.1199951171875,"duration":0.1300048828125,"other":"shape6","detail":"Cube.051"},{"actutorId":92,"timestamp":289.1199951171875,"duration":0.1300048828125,"other":"shape6","detail":"Cube.051"},{"actutorId":93,"timestamp":289.16998291015627,"duration":0.08001708984375,"other":"shape6","detail":"Cube.051"},{"actutorId":93,"timestamp":289.16998291015627,"duration":0.08001708984375,"other":"shape6","detail":"Cube.051"},{"actutorId":154,"timestamp":293.8699951171875,"duration":0.089996337890625,"other":"shape7","detail":"Cube.031"},{"actutorId":107,"timestamp":294.1199951171875,"duration":0.230010986328125,"other":"shape7","detail":"Cube.011"},{"actutorId":94,"timestamp":293.97998046875,"duration":0.75,"other":"shape7","detail":"Cube.011"},{"actutorId":109,"timestamp":293.8699951171875,"duration":0.709991455078125,"other":"shape7","detail":"Cube.047"},{"actutorId":93,"timestamp":294.6000061035156,"duration":0.279998779296875,"other":"shape7","detail":"Cube.049"},{"actutorId":108,"timestamp":293.8699951171875,"duration":1.260009765625,"other":"shape7","detail":"Cube.011"},{"actutorId":92,"timestamp":294.67999267578127,"duration":0.230010986328125,"other":"shape7","detail":"Cube.051"},{"actutorId":94,"timestamp":293.97998046875,"duration":0.75,"other":"shape7","detail":"Cube.011"},{"actutorId":92,"timestamp":294.67999267578127,"duration":0.230010986328125,"other":"shape7","detail":"Cube.051"},{"actutorId":129,"timestamp":293.82000732421877,"duration":1.029998779296875,"other":"shape7","detail":"Cube.019"},{"actutorId":93,"timestamp":294.6000061035156,"duration":0.279998779296875,"other":"shape7","detail":"Cube.049"},{"actutorId":93,"timestamp":294.6000061035156,"duration":0.279998779296875,"other":"shape7","detail":"Cube.049"},{"actutorId":92,"timestamp":294.67999267578127,"duration":0.230010986328125,"other":"shape7","detail":"Cube.051"},{"actutorId":130,"timestamp":293.7900085449219,"duration":1.22998046875,"other":"shape7","detail":"Cube.019"},{"actutorId":110,"timestamp":293.8699951171875,"duration":1.230010986328125,"other":"shape7","detail":"Cube.047"},{"actutorId":110,"timestamp":293.8699951171875,"duration":1.230010986328125,"other":"shape7","detail":"Cube.047"},{"actutorId":109,"timestamp":294.8299865722656,"duration":0.300018310546875,"other":"shape7","detail":"Cube.049"},{"actutorId":109,"timestamp":294.8299865722656,"duration":0.300018310546875,"other":"shape7","detail":"Cube.049"},{"actutorId":109,"timestamp":294.8299865722656,"duration":0.300018310546875,"other":"shape7","detail":"Cube.049"},{"actutorId":108,"timestamp":293.8699951171875,"duration":1.260009765625,"other":"shape7","detail":"Cube.011"},{"actutorId":152,"timestamp":293.8500061035156,"duration":1.319976806640625,"other":"shape7","detail":"Cube.036"},{"actutorId":153,"timestamp":294.5799865722656,"duration":0.589996337890625,"other":"shape7","detail":"Cube.036"},{"actutorId":153,"timestamp":294.5799865722656,"duration":0.589996337890625,"other":"shape7","detail":"Cube.036"},{"actutorId":153,"timestamp":294.5799865722656,"duration":0.589996337890625,"other":"shape7","detail":"Cube.036"},{"actutorId":154,"timestamp":294.8299865722656,"duration":0.339996337890625,"other":"shape7","detail":"Cube.035"},{"actutorId":154,"timestamp":294.8299865722656,"duration":0.339996337890625,"other":"shape7","detail":"Cube.035"},{"actutorId":154,"timestamp":294.8299865722656,"duration":0.339996337890625,"other":"shape7","detail":"Cube.035"},{"actutorId":154,"timestamp":294.8299865722656,"duration":0.339996337890625,"other":"shape7","detail":"Cube.035"},{"actutorId":97,"timestamp":299.91998291015627,"duration":0.120025634765625,"other":"shape8","detail":"Cube.009"},{"actutorId":96,"timestamp":299.91998291015627,"duration":0.180023193359375,"other":"shape8","detail":"Cube.009"},{"actutorId":164,"timestamp":305.91998291015627,"duration":0.029998779296875,"other":"shape9","detail":"Cube.011"},{"actutorId":165,"timestamp":305.91998291015627,"duration":0.420013427734375,"other":"shape9","detail":"Cube.011"},{"actutorId":75,"timestamp":306.9100036621094,"duration":0.139984130859375,"other":"shape9","detail":"Cube.009"},{"actutorId":74,"timestamp":306.9100036621094,"duration":0.139984130859375,"other":"shape9","detail":"Cube.009"},{"actutorId":98,"timestamp":306.8800048828125,"duration":0.199981689453125,"other":"shape9","detail":"Cube.009"},{"actutorId":96,"timestamp":306.67999267578127,"duration":0.480010986328125,"other":"shape9","detail":"Cube.009"},{"actutorId":97,"timestamp":306.67999267578127,"duration":0.480010986328125,"other":"shape9","detail":"Cube.009"},{"actutorId":103,"timestamp":310.53997802734377,"duration":0.030029296875,"other":"shape10","detail":"Cube.020"},{"actutorId":99,"timestamp":310.5899963378906,"duration":0.019989013671875,"other":"shape10","detail":"Cube.020"},{"actutorId":107,"timestamp":310.57000732421877,"duration":0.80999755859375,"other":"shape10","detail":"Cube.036"},{"actutorId":107,"timestamp":310.57000732421877,"duration":0.80999755859375,"other":"shape10","detail":"Cube.036"},{"actutorId":104,"timestamp":310.53997802734377,"duration":0.160003662109375,"other":"shape10","detail":"Cube.020"},{"actutorId":167,"timestamp":310.66998291015627,"duration":0.029998779296875,"other":"shape10","detail":"Cube.014"},{"actutorId":167,"timestamp":310.66998291015627,"duration":0.029998779296875,"other":"shape10","detail":"Cube.014"},{"actutorId":106,"timestamp":310.54998779296877,"duration":0.170013427734375,"other":"shape10","detail":"Cube.035"},{"actutorId":106,"timestamp":310.54998779296877,"duration":0.170013427734375,"other":"shape10","detail":"Cube.035"},{"actutorId":168,"timestamp":310.66998291015627,"duration":0.08001708984375,"other":"shape10","detail":"Cube.014"},{"actutorId":157,"timestamp":310.6399841308594,"duration":0.30999755859375,"other":"shape10","detail":"Cube.010"},{"actutorId":95,"timestamp":310.8999938964844,"duration":0.660003662109375,"other":"shape10","detail":"Cube.031"},{"actutorId":155,"timestamp":310.66998291015627,"duration":0.55999755859375,"other":"shape10","detail":"Cube.010"},{"actutorId":104,"timestamp":311.03997802734377,"duration":0.220001220703125,"other":"shape10","detail":"Cube.020"},{"actutorId":76,"timestamp":310.66998291015627,"duration":0.670013427734375,"other":"shape10","detail":"Cube.020"},{"actutorId":98,"timestamp":310.5899963378906,"duration":0.699981689453125,"other":"shape10","detail":"Cube.020"},{"actutorId":78,"timestamp":310.6999816894531,"duration":0.589996337890625,"other":"shape10","detail":"Cube.036"},{"actutorId":106,"timestamp":311.05999755859377,"duration":0.260009765625,"other":"shape10","detail":"Cube.035"},{"actutorId":106,"timestamp":311.05999755859377,"duration":0.260009765625,"other":"shape10","detail":"Cube.035"},{"actutorId":211,"timestamp":310.8299865722656,"duration":0.490020751953125,"other":"shape10","detail":"Cube.049"},{"actutorId":77,"timestamp":310.6999816894531,"duration":0.680023193359375,"other":"shape10","detail":"Cube.035"},{"actutorId":76,"timestamp":310.66998291015627,"duration":0.670013427734375,"other":"shape10","detail":"Cube.020"},{"actutorId":105,"timestamp":310.54998779296877,"duration":0.8800048828125,"other":"shape10","detail":"Cube.031"},{"actutorId":107,"timestamp":310.57000732421877,"duration":0.80999755859375,"other":"shape10","detail":"Cube.036"},{"actutorId":77,"timestamp":310.6999816894531,"duration":0.680023193359375,"other":"shape10","detail":"Cube.035"},{"actutorId":77,"timestamp":310.6999816894531,"duration":0.680023193359375,"other":"shape10","detail":"Cube.035"},{"actutorId":105,"timestamp":310.54998779296877,"duration":0.8800048828125,"other":"shape10","detail":"Cube.031"},{"actutorId":95,"timestamp":310.8999938964844,"duration":0.660003662109375,"other":"shape10","detail":"Cube.031"},{"actutorId":97,"timestamp":310.5899963378906,"duration":0.8599853515625,"other":"shape10","detail":"Cube.020"},{"actutorId":94,"timestamp":311.3999938964844,"duration":0.489990234375,"other":"shape10","detail":"Cube.036"},{"actutorId":157,"timestamp":311.42999267578127,"duration":0.04998779296875,"other":"shape10","detail":"Cube.010"},{"actutorId":95,"timestamp":310.8999938964844,"duration":0.660003662109375,"other":"shape10","detail":"Cube.031"},{"actutorId":157,"timestamp":311.5899963378906,"duration":0.029998779296875,"other":"shape10","detail":"Cube.010"},{"actutorId":94,"timestamp":311.3999938964844,"duration":0.489990234375,"other":"shape10","detail":"Cube.036"},{"actutorId":94,"timestamp":311.3999938964844,"duration":0.489990234375,"other":"shape10","detail":"Cube.036"},{"actutorId":156,"timestamp":310.66998291015627,"duration":1.1300048828125,"other":"shape10","detail":"Cube.010"},{"actutorId":166,"timestamp":310.6399841308594,"duration":1.25,"other":"shape10","detail":"Cube.007"},{"actutorId":163,"timestamp":310.57000732421877,"duration":1.25,"other":"shape10","detail":"Cube.010"},{"actutorId":211,"timestamp":311.7699890136719,"duration":0.30999755859375,"other":"shape10","detail":"Cube.047"},{"actutorId":125,"timestamp":310.5899963378906,"duration":1.230010986328125,"other":"shape10","detail":"Cube.010"},{"actutorId":125,"timestamp":310.5899963378906,"duration":1.230010986328125,"other":"shape10","detail":"Cube.010"},{"actutorId":164,"timestamp":310.5899963378906,"duration":1.25,"other":"shape10","detail":"Cube.010"},{"actutorId":95,"timestamp":311.67999267578127,"duration":0.17999267578125,"other":"shape10","detail":"Cube.036"},{"actutorId":95,"timestamp":311.67999267578127,"duration":0.17999267578125,"other":"shape10","detail":"Cube.036"},{"actutorId":95,"timestamp":311.67999267578127,"duration":0.17999267578125,"other":"shape10","detail":"Cube.036"},{"actutorId":165,"timestamp":310.5899963378906,"duration":1.269989013671875,"other":"shape10","detail":"Cube.010"},{"actutorId":136,"timestamp":310.6099853515625,"duration":1.25,"other":"shape10","detail":"Cube.010"},{"actutorId":96,"timestamp":310.6099853515625,"duration":1.279998779296875,"other":"shape10","detail":"Cube.020"},{"actutorId":96,"timestamp":310.6099853515625,"duration":1.279998779296875,"other":"shape10","detail":"Cube.020"},{"actutorId":166,"timestamp":310.6399841308594,"duration":1.25,"other":"shape10","detail":"Cube.007"},{"actutorId":94,"timestamp":311.3999938964844,"duration":0.489990234375,"other":"shape10","detail":"Cube.036"},{"actutorId":212,"timestamp":310.8299865722656,"duration":1.260009765625,"other":"shape10","detail":"Cube.016"},{"actutorId":211,"timestamp":311.7699890136719,"duration":0.30999755859375,"other":"shape10","detail":"Cube.047"},{"actutorId":213,"timestamp":310.8299865722656,"duration":1.260009765625,"other":"shape10","detail":"Cube.047"},{"actutorId":211,"timestamp":311.7699890136719,"duration":0.30999755859375,"other":"shape10","detail":"Cube.047"},{"actutorId":212,"timestamp":310.8299865722656,"duration":1.260009765625,"other":"shape10","detail":"Cube.016"},{"actutorId":212,"timestamp":310.8299865722656,"duration":1.260009765625,"other":"shape10","detail":"Cube.016"},{"actutorId":213,"timestamp":310.8299865722656,"duration":1.260009765625,"other":"shape10","detail":"Cube.047"},{"actutorId":212,"timestamp":310.8299865722656,"duration":1.260009765625,"other":"shape10","detail":"Cube.016"},{"actutorId":66,"timestamp":316.6600036621094,"duration":0.05999755859375,"other":"shape11","detail":"Cube.019"},{"actutorId":139,"timestamp":316.6600036621094,"duration":1.269989013671875,"other":"shape11","detail":"Cube.011"},{"actutorId":75,"timestamp":316.7200012207031,"duration":0.029998779296875,"other":"shape11","detail":"Cube.019"},{"actutorId":102,"timestamp":316.6000061035156,"duration":0.239990234375,"other":"shape11","detail":"Cube.019"},{"actutorId":99,"timestamp":316.6600036621094,"duration":0.17999267578125,"other":"shape11","detail":"Cube.019"},{"actutorId":67,"timestamp":316.6300048828125,"duration":0.259979248046875,"other":"shape11","detail":"Cube.019"},{"actutorId":140,"timestamp":316.91998291015627,"duration":0.029998779296875,"other":"shape11","detail":"Cube.051"},{"actutorId":74,"timestamp":316.6999816894531,"duration":0.279998779296875,"other":"shape11","detail":"Cube.019"},{"actutorId":163,"timestamp":316.9499816894531,"duration":0.30999755859375,"other":"shape11","detail":"Cube.010"},{"actutorId":140,"timestamp":317.22998046875,"duration":0.70001220703125,"other":"shape11","detail":"Cube.049"},{"actutorId":94,"timestamp":316.91998291015627,"duration":0.470001220703125,"other":"shape11","detail":"Cube.035"},{"actutorId":94,"timestamp":316.91998291015627,"duration":0.470001220703125,"other":"shape11","detail":"Cube.035"},{"actutorId":93,"timestamp":316.7200012207031,"duration":0.759979248046875,"other":"shape11","detail":"Cube.036"},{"actutorId":65,"timestamp":317.5899963378906,"duration":0.1099853515625,"other":"shape11","detail":"Cube.019"},{"actutorId":104,"timestamp":317.55999755859377,"duration":0.16998291015625,"other":"shape11","detail":"Cube.019"},{"actutorId":74,"timestamp":317.3500061035156,"duration":0.40997314453125,"other":"shape11","detail":"Cube.019"},{"actutorId":66,"timestamp":317.47998046875,"duration":0.370025634765625,"other":"shape11","detail":"Cube.019"},{"actutorId":73,"timestamp":316.6600036621094,"duration":1.19000244140625,"other":"shape11","detail":"Cube.019"},{"actutorId":103,"timestamp":317.5099792480469,"duration":0.34002685546875,"other":"shape11","detail":"Cube.019"},{"actutorId":99,"timestamp":317.42999267578127,"duration":0.420013427734375,"other":"shape11","detail":"Cube.019"},{"actutorId":67,"timestamp":317.3699951171875,"duration":0.540008544921875,"other":"shape11","detail":"Cube.019"},{"actutorId":72,"timestamp":316.6600036621094,"duration":1.25,"other":"shape11","detail":"Cube.019"},{"actutorId":102,"timestamp":317.3899841308594,"duration":0.52001953125,"other":"shape11","detail":"Cube.019"},{"actutorId":164,"timestamp":316.6300048828125,"duration":1.279998779296875,"other":"shape11","detail":"Cube.010"},{"actutorId":165,"timestamp":316.6300048828125,"duration":1.279998779296875,"other":"shape11","detail":"Cube.010"},{"actutorId":100,"timestamp":316.6300048828125,"duration":1.279998779296875,"other":"shape11","detail":"Cube.019"},{"actutorId":140,"timestamp":317.22998046875,"duration":0.70001220703125,"other":"shape11","detail":"Cube.049"},{"actutorId":68,"timestamp":316.6300048828125,"duration":1.29998779296875,"other":"shape11","detail":"Cube.019"},{"actutorId":71,"timestamp":316.6300048828125,"duration":1.29998779296875,"other":"shape11","detail":"Cube.019"},{"actutorId":101,"timestamp":316.6000061035156,"duration":1.329986572265625,"other":"shape11","detail":"Cube.019"},{"actutorId":140,"timestamp":317.22998046875,"duration":0.70001220703125,"other":"shape11","detail":"Cube.049"},{"actutorId":139,"timestamp":316.6600036621094,"duration":1.269989013671875,"other":"shape11","detail":"Cube.011"},{"actutorId":69,"timestamp":316.6000061035156,"duration":1.3599853515625,"other":"shape11","detail":"Cube.019"},{"actutorId":93,"timestamp":317.9100036621094,"duration":0.04998779296875,"other":"shape11","detail":"Cube.036"},{"actutorId":94,"timestamp":317.9100036621094,"duration":0.04998779296875,"other":"shape11","detail":"Cube.036"},{"actutorId":94,"timestamp":317.9100036621094,"duration":0.04998779296875,"other":"shape11","detail":"Cube.036"},{"actutorId":94,"timestamp":317.9100036621094,"duration":0.04998779296875,"other":"shape11","detail":"Cube.036"},{"actutorId":70,"timestamp":316.6000061035156,"duration":1.389984130859375,"other":"shape11","detail":"Cube.019"},{"actutorId":96,"timestamp":322.6999816894531,"duration":0.5,"other":"shape12","detail":"Cube.011"},{"actutorId":164,"timestamp":329.2099914550781,"duration":0.110015869140625,"other":"shape13","detail":"Cube.009"},{"actutorId":125,"timestamp":329.0899963378906,"duration":0.350006103515625,"other":"shape13","detail":"Cube.009"},{"actutorId":136,"timestamp":329.0899963378906,"duration":0.350006103515625,"other":"shape13","detail":"Cube.009"},{"actutorId":166,"timestamp":329.0299987792969,"duration":0.42999267578125,"other":"shape13","detail":"Cube.009"},{"actutorId":165,"timestamp":328.97998046875,"duration":0.529998779296875,"other":"shape13","detail":"Cube.009"},{"actutorId":169,"timestamp":336.1399841308594,"duration":0.25,"other":"shape14","detail":"Cube.035"},{"actutorId":169,"timestamp":336.1399841308594,"duration":0.25,"other":"shape14","detail":"Cube.035"},{"actutorId":97,"timestamp":336.16998291015627,"duration":1.050018310546875,"other":"shape14","detail":"Cube.011"},{"actutorId":154,"timestamp":336.0799865722656,"duration":0.42999267578125,"other":"shape14","detail":"Cube.031"},{"actutorId":93,"timestamp":336.6099853515625,"duration":0.6199951171875,"other":"shape14","detail":"Cube.011"},{"actutorId":155,"timestamp":335.9700012207031,"duration":1.009979248046875,"other":"shape14","detail":"Cube.020"},{"actutorId":105,"timestamp":336.97998046875,"duration":0.19000244140625,"other":"shape14","detail":"Cube.011"},{"actutorId":104,"timestamp":336.92999267578127,"duration":0.25,"other":"shape14","detail":"Cube.011"},{"actutorId":104,"timestamp":336.92999267578127,"duration":0.25,"other":"shape14","detail":"Cube.011"},{"actutorId":103,"timestamp":336.80999755859377,"duration":0.3699951171875,"other":"shape14","detail":"Cube.007"},{"actutorId":103,"timestamp":336.80999755859377,"duration":0.3699951171875,"other":"shape14","detail":"Cube.007"},{"actutorId":102,"timestamp":336.7599792480469,"duration":0.420013427734375,"other":"shape14","detail":"Cube.011"},{"actutorId":102,"timestamp":336.7599792480469,"duration":0.420013427734375,"other":"shape14","detail":"Cube.011"},{"actutorId":101,"timestamp":336.6999816894531,"duration":0.480010986328125,"other":"shape14","detail":"Cube.007"},{"actutorId":152,"timestamp":335.9700012207031,"duration":1.29998779296875,"other":"shape14","detail":"Cube.036"},{"actutorId":69,"timestamp":336.9499816894531,"duration":0.27001953125,"other":"shape14","detail":"Cube.007"},{"actutorId":70,"timestamp":336.80999755859377,"duration":0.389984130859375,"other":"shape14","detail":"Cube.007"},{"actutorId":99,"timestamp":336.5899963378906,"duration":0.6300048828125,"other":"shape14","detail":"Cube.007"},{"actutorId":100,"timestamp":336.5899963378906,"duration":0.6099853515625,"other":"shape14","detail":"Cube.007"},{"actutorId":69,"timestamp":336.9499816894531,"duration":0.27001953125,"other":"shape14","detail":"Cube.007"},{"actutorId":97,"timestamp":336.16998291015627,"duration":1.050018310546875,"other":"shape14","detail":"Cube.011"},{"actutorId":98,"timestamp":336.4499816894531,"duration":0.77001953125,"other":"shape14","detail":"Cube.007"},{"actutorId":98,"timestamp":336.4499816894531,"duration":0.77001953125,"other":"shape14","detail":"Cube.007"},{"actutorId":99,"timestamp":336.5899963378906,"duration":0.6300048828125,"other":"shape14","detail":"Cube.007"},{"actutorId":94,"timestamp":335.91998291015627,"duration":1.300018310546875,"other":"shape14","detail":"Cube.011"},{"actutorId":95,"timestamp":336.5899963378906,"duration":0.6300048828125,"other":"shape14","detail":"Cube.011"},{"actutorId":72,"timestamp":336.7599792480469,"duration":0.5,"other":"shape14","detail":"Cube.007"},{"actutorId":71,"timestamp":336.6999816894531,"duration":0.529998779296875,"other":"shape14","detail":"Cube.007"},{"actutorId":96,"timestamp":336.16998291015627,"duration":1.05999755859375,"other":"shape14","detail":"Cube.011"},{"actutorId":92,"timestamp":335.94000244140627,"duration":1.28997802734375,"other":"shape14","detail":"Cube.010"},{"actutorId":92,"timestamp":335.94000244140627,"duration":1.28997802734375,"other":"shape14","detail":"Cube.010"},{"actutorId":93,"timestamp":336.6099853515625,"duration":0.6199951171875,"other":"shape14","detail":"Cube.011"},{"actutorId":73,"timestamp":336.78997802734377,"duration":0.470001220703125,"other":"shape14","detail":"Cube.011"},{"actutorId":73,"timestamp":336.78997802734377,"duration":0.470001220703125,"other":"shape14","detail":"Cube.011"},{"actutorId":72,"timestamp":336.7599792480469,"duration":0.5,"other":"shape14","detail":"Cube.007"},{"actutorId":151,"timestamp":335.9700012207031,"duration":1.29998779296875,"other":"shape14","detail":"Cube.036"},{"actutorId":152,"timestamp":335.9700012207031,"duration":1.29998779296875,"other":"shape14","detail":"Cube.036"},{"actutorId":152,"timestamp":335.9700012207031,"duration":1.29998779296875,"other":"shape14","detail":"Cube.036"},{"actutorId":152,"timestamp":335.9700012207031,"duration":1.29998779296875,"other":"shape14","detail":"Cube.036"},{"actutorId":75,"timestamp":336.92999267578127,"duration":0.339996337890625,"other":"shape14","detail":"Cube.011"},{"actutorId":74,"timestamp":336.8399963378906,"duration":0.42999267578125,"other":"shape14","detail":"Cube.011"},{"actutorId":74,"timestamp":336.8399963378906,"duration":0.42999267578125,"other":"shape14","detail":"Cube.011"},{"actutorId":154,"timestamp":337.03997802734377,"duration":0.240020751953125,"other":"shape14","detail":"Cube.020"},{"actutorId":153,"timestamp":335.9700012207031,"duration":1.29998779296875,"other":"shape14","detail":"Cube.031"},{"actutorId":76,"timestamp":336.8399963378906,"duration":0.42999267578125,"other":"shape14","detail":"Cube.011"},{"actutorId":153,"timestamp":335.9700012207031,"duration":1.29998779296875,"other":"shape14","detail":"Cube.031"},{"actutorId":153,"timestamp":335.9700012207031,"duration":1.29998779296875,"other":"shape14","detail":"Cube.031"},{"actutorId":153,"timestamp":335.9700012207031,"duration":1.29998779296875,"other":"shape14","detail":"Cube.031"},{"actutorId":154,"timestamp":337.03997802734377,"duration":0.240020751953125,"other":"shape14","detail":"Cube.020"},{"actutorId":77,"timestamp":336.8399963378906,"duration":0.459991455078125,"other":"shape14","detail":"Cube.011"},{"actutorId":79,"timestamp":336.97998046875,"duration":0.33001708984375,"other":"shape14","detail":"Cube.011"},{"actutorId":78,"timestamp":336.8699951171875,"duration":0.44000244140625,"other":"shape14","detail":"Cube.011"},{"actutorId":139,"timestamp":342.0799865722656,"duration":0.089996337890625,"other":"shape15","detail":"Cube.035"},{"actutorId":139,"timestamp":342.0799865722656,"duration":0.089996337890625,"other":"shape15","detail":"Cube.035"},{"actutorId":169,"timestamp":342.0799865722656,"duration":0.1400146484375,"other":"shape15","detail":"Cube.035"},{"actutorId":169,"timestamp":342.0799865722656,"duration":0.1400146484375,"other":"shape15","detail":"Cube.035"},{"actutorId":168,"timestamp":342.0799865722656,"duration":0.3699951171875,"other":"shape15","detail":"Cube.020"},{"actutorId":99,"timestamp":341.8800048828125,"duration":0.629974365234375,"other":"shape15","detail":"Cube.007"},{"actutorId":100,"timestamp":341.8800048828125,"duration":0.569976806640625,"other":"shape15","detail":"Cube.007"},{"actutorId":168,"timestamp":342.0799865722656,"duration":0.3699951171875,"other":"shape15","detail":"Cube.020"},{"actutorId":98,"timestamp":341.8800048828125,"duration":0.72998046875,"other":"shape15","detail":"Cube.007"},{"actutorId":99,"timestamp":341.8800048828125,"duration":0.629974365234375,"other":"shape15","detail":"Cube.007"},{"actutorId":95,"timestamp":341.8800048828125,"duration":0.629974365234375,"other":"shape15","detail":"Cube.011"},{"actutorId":157,"timestamp":341.9700012207031,"duration":0.569976806640625,"other":"shape15","detail":"Cube.020"},{"actutorId":98,"timestamp":341.8800048828125,"duration":0.72998046875,"other":"shape15","detail":"Cube.007"},{"actutorId":152,"timestamp":342.5099792480469,"duration":0.800018310546875,"other":"shape15","detail":"Cube.036"},{"actutorId":152,"timestamp":342.5099792480469,"duration":0.800018310546875,"other":"shape15","detail":"Cube.036"},{"actutorId":153,"timestamp":342.7799987792969,"duration":0.529998779296875,"other":"shape15","detail":"Cube.035"},{"actutorId":152,"timestamp":342.5099792480469,"duration":0.800018310546875,"other":"shape15","detail":"Cube.036"},{"actutorId":156,"timestamp":342.0,"duration":0.91998291015625,"other":"shape15","detail":"Cube.020"},{"actutorId":92,"timestamp":341.9100036621094,"duration":1.319976806640625,"other":"shape15","detail":"Cube.011"},{"actutorId":155,"timestamp":342.0,"duration":1.1199951171875,"other":"shape15","detail":"Cube.020"},{"actutorId":100,"timestamp":342.91998291015627,"duration":0.230010986328125,"other":"shape15","detail":"Cube.007"},{"actutorId":96,"timestamp":343.1499938964844,"duration":0.079986572265625,"other":"shape15","detail":"Cube.011"},{"actutorId":97,"timestamp":341.9100036621094,"duration":1.319976806640625,"other":"shape15","detail":"Cube.007"},{"actutorId":98,"timestamp":342.7799987792969,"duration":0.42999267578125,"other":"shape15","detail":"Cube.007"},{"actutorId":98,"timestamp":342.7799987792969,"duration":0.42999267578125,"other":"shape15","detail":"Cube.007"},{"actutorId":99,"timestamp":342.80999755859377,"duration":0.399993896484375,"other":"shape15","detail":"Cube.007"},{"actutorId":94,"timestamp":341.9100036621094,"duration":1.29998779296875,"other":"shape15","detail":"Cube.011"},{"actutorId":95,"timestamp":342.7799987792969,"duration":0.42999267578125,"other":"shape15","detail":"Cube.011"},{"actutorId":96,"timestamp":343.1499938964844,"duration":0.079986572265625,"other":"shape15","detail":"Cube.011"},{"actutorId":97,"timestamp":341.9100036621094,"duration":1.319976806640625,"other":"shape15","detail":"Cube.007"},{"actutorId":92,"timestamp":341.9100036621094,"duration":1.319976806640625,"other":"shape15","detail":"Cube.011"},{"actutorId":93,"timestamp":341.9100036621094,"duration":1.319976806640625,"other":"shape15","detail":"Cube.011"},{"actutorId":91,"timestamp":342.80999755859377,"duration":0.449981689453125,"other":"shape15","detail":"Cube.011"},{"actutorId":91,"timestamp":342.80999755859377,"duration":0.449981689453125,"other":"shape15","detail":"Cube.011"},{"actutorId":130,"timestamp":343.1199951171875,"duration":0.19000244140625,"other":"shape15","detail":"Cube.019"},{"actutorId":152,"timestamp":342.5099792480469,"duration":0.800018310546875,"other":"shape15","detail":"Cube.036"},{"actutorId":153,"timestamp":342.7799987792969,"duration":0.529998779296875,"other":"shape15","detail":"Cube.035"},{"actutorId":153,"timestamp":342.7799987792969,"duration":0.529998779296875,"other":"shape15","detail":"Cube.035"},{"actutorId":153,"timestamp":342.7799987792969,"duration":0.529998779296875,"other":"shape15","detail":"Cube.035"},{"actutorId":153,"timestamp":342.7799987792969,"duration":0.529998779296875,"other":"shape15","detail":"Cube.035"},{"actutorId":154,"timestamp":342.0,"duration":1.339996337890625,"other":"shape15","detail":"Cube.031"},{"actutorId":154,"timestamp":342.0,"duration":1.339996337890625,"other":"shape15","detail":"Cube.031"}]}